{"0001": ["HG/79", "06.30", "gi\u1ea5y", "7 D"], "0002": [], "0003": [], "0004": ["08/0/079", "06:30:2", "1", "1", "gia", "0", "7772"], "0005": ["11/000", "06:30"], "0006": ["Giollap", "06:30:31", "3", "03/000 10:45", "45", "3/38"], "0007": ["Phi P.C", "HIV9", "08.3020", "1"], "0008": [], "0009": ["HT/0790"], "0010": ["Cozing", "06:30:54"], "0011": ["HG/79", "06:30:55", "a", "7/1"], "0012": ["HI/79", "06:31:06", "1", "60", "H\u1ea2I TRI\u1ec0U", "7712"], "0013": ["H7M9HD", "06:31:04"], "0014": [], "0015": ["1017", "06:31:14", "3", "Giang 1, To\u00e1n", "469", "176"], "0016": ["FAHA", "HT/Q", "06:31", "39", "L\u00ca HOI", "D\u01af\u01a0NG SA", "2023"], "0017": ["Li\u00ean 19/70", "06:31:19", "FAHASA", "FAHASZ", "FAHASA", "3", "9", "1", "03", "1", "6 B\u1ecb", "/37", "\u0110\u01af\u1edcNG S\u00c1CH", "T\u1ebeT G", "QU\u00dd M\u00c1C", "\u0110\u1ed0N 800.000 L\u01af\u1ee2T KH\u00c1CH TH\u00c0M QUAN"], "0018": ["1011"], "0019": ["1", "H\u1ed3/79", "13/23", "06:31:27", "5", "3", "58", "Thu\u1eadn t\u00e2y thu\u1ef7 thu\u1ef7 c\u00f4ng c\u00f4ng c\u1ed9ng c\u1ed9ng c\u1ed9ng c\u1ed9ng c\u1ed9ng c\u1ed9ng c\u1ed9ng c\u1ed9ng c\u1ed9ng c\u1ed9ng c\u1ed9ng c\u1ed9ng c\u1ed9ng c\u1ed9ng c\u1ed9ng c\u1ed9ng c\u1ed9ng c\u1ed9ng c\u1ed9ng c\u1ed9ng", "1", "T\u1ed5 1", "17:17", "13:2"], "0020": ["69077,000", "06:31:30", "CHANHGING", "Co", "NH\u1eeeNG B\u00c0 H\u1eccC, THI\u1ebeN THU\u00dd", "0", "\u0110\u1ec0 G\u1ea6N DUNG MOI DONNA NGHI\u1ec6P TH\u00c0NH T\u00d4NG", "C\u1ed5", "1", "MATT BLUMPER"], "0021": ["6000", "QMEGA", "06:31:38", "\u0110\u1ea1i", "13", "E", "6", "Vai", "a", "1", "3", "TUDU", "3", "200", "1"], "0022": ["899", "12", "H7/V9H", "06:31", "412:", "Vi", "T\u01af DUY", "3", "1", "1"], "0023": ["HO/79", "H\u0110", "06:31", "19", "Nai", "290"], "0024": ["HT/VQ", "06:31:42", "113", "23", "200"], "0025": ["6Cha", "6/0/70", "43/06:31:47", "4100", "952673", "Po13", "102"], "0026": ["HTVQ", "0631850"], "0027": ["14/71220", "06:31:59", "1", "12/11", "Tinh", "200"], "0028": [], "0029": ["Co17a0", "06:31:57"], "0030": ["Co17:00", "06:32:04", "TO", "1"], "0031": ["Gi\u1eddi t\u00e2y", "06:32:10", "1", "1"], "0032": ["Cogon cao", "06:32:14"], "0033": ["HG/VG", "06:32:1", "\u1ed1c", "TH\u1edcI", "C\u00d4NG NGHE", "GI\u00c1M:", "HOP", "0"], "0034": ["HT/079", "06:32:23"], "0035": ["HT/79", "06:32:24"], "0036": ["H7/079", "06:32:"], "0037": [], "0038": ["HT/VG", "06:32:36"], "0039": ["HT/VQ", "06:32:", "DI SUBSCRIBED"], "0040": ["HT/V9", "06:32:4", "2.3:33"], "0041": ["HG/79", "06:32-46"], "0042": ["HT/VQ", "06:32:48", "22"], "0043": [], "0044": [], "0045": ["13/0720", "06:32:55"], "0046": ["H117 a", "H\u1ee2P T\u00c1C X\u00c1", "06:32:58", "THU\u1ea6N - CH\u1ea2O TH\u00c0NH", "\u0110T: 0985"], "0047": ["03", "HG/79", "06:33:04", "C7RA"], "0048": ["HG/V79", "06:33:04", "1"], "0049": ["Cigona", "06:33:07"], "0050": ["HT/VO", "06.33:09"], "0051": [], "0052": ["HT/V7QN", "06:33"], "0053": ["1020", "HO/70", "10/000", "06:33:1", "1"], "0054": ["HI/VI", "06:331", "1", "V71"], "0055": ["HGI\u1edc QU\u1ea2", "06:33:24", "72"], "0056": ["HI/70", "06:33:22", "gio", "772"], "0057": ["47/079", "06:33:38", "0", "721"], "0058": ["HG/V", "06:33:35", "11"], "0059": ["GI\u1ec07", "0638", "a"], "0060": ["HT/V7QN", "06:33:48"], "0061": ["18", "12/1020 2020", "8232", "Lu:o:", "19", "NG\u01afY", "VON", "T\u1ea0I LI\u00c0"], "0062": ["HT/V", "1", "52000 Li", "111", "H"], "0063": ["1", "1225", "3/1", "FP HI"], "0064": ["CH\u01af\u01a0NG", "HG/V", "06:34:00"], "0065": ["CH\u01af\u01a0NG TR\u00ccNH 60 GI\u00c1", "HO/79", "30 TREN", "06:34"], "0066": ["HT/VQ", "06:34:1"], "0067": ["HT/V7QN", "06:34:16", "13"], "0068": ["HG/7", "06:34:34", "E"], "0069": ["HT/7", "06-34", "C\u1ea9m"], "0070": ["G\u00f2ng 176", "06:34:24", "3"], "0071": [], "0072": ["HT/V9", "06:34:33", "NGUY", "DU KH\u00c1CH THAM C\u1ea8M", "QUAN"], "0073": ["HG/79", "06:34:36"], "0074": ["P529"], "0075": ["HT/VQ", "06:3443"], "0076": ["16/017:20", "06:3446"], "0077": ["Co17020", "06:3448"], "0078": ["Collap", "06:34:55"], "0079": ["Coop", "06:34:59"], "0080": ["C1777 Qu\u1ea3", "06:35:02", "TU KH\u00c1CH NG\u00c0", "MOO", "T\u1ed4NG TR\u1ec0N CH\u1ee2 N\u1ed4I LONG XUY\u00caN", "V\u00c0 2"], "0081": ["Gi\u1edd 7/7000", "-06:35:07", "1500", "07 2", "1", "2", "DU KH\u00c1CH", "CH NG\u00c0", "MAT", "MOO", "V\u00c0 \u0102N S\u00c1NG TR\u1ec0N CH\u1ee2 N\u1ed4I LONG XUY\u00caN"], "0082": ["19/5/07", "9", "06:35:09"], "0083": ["617/702000", "06:35:12"], "0084": ["HT/79", "06:35:17"], "0085": ["Ho\u00e0ng chu", "06:35:20"], "0086": ["Gi\u1eddi Van", "06:35:25", "L\u00ca KIM", "TH\u00c1I \u0110\u1ed2, NGU X\u00e3 M\u1ef8 HOA H\u01afNG, TP LONG XUY\u00caN"], "0087": ["G/7/79", "06:35:30"], "0088": ["HTMIN", "06:35:33"], "0089": ["HT/79", "0635:38", "1", "1"], "0090": ["HT/79", "06:35:40", "6", "1"], "0091": ["H7/VIN", "06:35:46"], "0092": ["HT/V90", "06:35:49", "132", "2"], "0093": ["VF 16/000 10/000", "06:35:53"], "0094": ["HT.79", "06:36:00"], "0095": ["0", "4/0", "06:36:04"], "0096": ["Giang", "06:36:08"], "0097": ["1", "71", "Co17:00", "MA", "7", "1", "12/00", "9"], "0098": ["1", "Chuy", "1", "33", "06:36:14", "5", "\u0110\u00d4NG 1", "T\u1ed4 DU KH\u00c1CH TH\u1ea6P PH\u01af\u01a0NG", "T\u00ccM \u0110\u1ebeN X\u1eec - HOA V\u00c0NG 0", "C\u00d3 XANH"], "0099": ["6/70/902", "06:36:21", "1"], "0100": ["Cogitan", "06:36:26"], "0101": ["Cogitan", "06:36:30", "10", "9:"], "0102": ["1", "H7/07Qui", "06:36:33", "13", "1", "1", "1"], "0103": ["Tailing", "11101"], "0104": ["47,", "H7/V9", "03", "06:36:36"], "0105": ["617020", "06:36:40"], "0106": ["100720", "06:36849"], "0107": [], "0108": ["HT/V9H1", "06:36:50", "53", "1"], "0109": ["HT/V91", "3000", "06:36:53"], "0110": ["HI/VIN", "06:36:53"], "0111": ["1", "Carva", "06:36:56"], "0112": ["H7/V9", "3222000", "06:36:58"], "0113": ["Cogon cap", "06:37:01"], "0114": ["Co.op cao duce", "06:37:08", "TO"], "0115": ["Co17:20", "06:37:14", "1"], "0116": ["HG/V9", "06:37:19", "6"], "0117": [], "0118": ["HG/V7", "79", "06:37:28"], "0119": ["08", "677/079", "0751 81", "06:37:33", "43 T5"], "0120": ["677079", "06:37:35"], "0121": ["6/7/070", "06:37:39", "6", "Toan"], "0122": ["HT/V940", "1", "06:37:48", "T\u1ed4NG T\u1ea0I H\u1eca \u0110\u1eca V\u0102N \u0110\u1eca T\u1ed4", "2T 11", "T\u1ed5 8 L", "1.47", "Vi", "3.300", "100.003", "1", "Gia", "E", "ES"], "0123": ["Co7on", "06:37:47", "T\u1ed4NG DONG S\u1ed0", "Tung T", "308-038"], "0124": ["6/779", "06:37:49"], "0125": ["13", "47 nay", "1", "HG/VG", "06:37:55", "19", "1"], "0126": ["2", "1", "6/0179", "06:37:58", "1", "2", "1", "13:"], "0127": ["HT/V9", "06:38:03"], "0128": [], "0129": [], "0130": ["Cogner", "06:38:12", "th\u00e1ng"], "0131": ["C1007900", "06:38:15", "2"], "0132": ["11/19", "06:38:"], "0133": ["1", "S\u1ed1 (343)", "3.10", "H7/0790", "1", "06:38:2"], "0134": ["a", "HT/07940", "06:38:24", "Collic", "THEO", "2.040 TI\u1ec0U"], "0135": ["HT/70", "06:38:26", "HEO"], "0136": ["6/017:00", "06:38:28", "1", "1"], "0137": ["HT/VQN", "06:38:32", "THEO"], "0138": ["10", "GIA", "06:39:16"], "0139": ["HT.79", "06:39:23", "1"], "0140": ["1", "G\u1ecd (BA)", "13", "H7/0790", "4", "06:39:29"], "0141": ["HT/V940", "06:39:38", "1", "VITA", "4", "1"], "0142": ["HG/79", "06:39:34", "1", "1", "GI3", "610", "HONG", "THUA", "TREN", "\u0110\u01af\u1edcNG HUY\u1ebeT M\u1ea0CH MI\u1ec0N T\u00c2Y", "LI\u1ec6T C\u1ea2 NG\u00c0Y"], "0143": ["Cogitan", "06:3940", "1", "TH TI\u1ec0N"], "0144": ["Co170 cao", "06:39:47"], "0145": ["HI/70", "06/39:5", "1"], "0146": ["H7/07940", "06:39:58", "Enlia", "P.AHULL"], "0147": ["HT/VQ", "06:40:03"], "0148": ["Ch\u1eddi Tao", "06:40:08", "Oexpo", ":", "1", "Ca", "1", "8"], "0149": ["617/702", "GIA", "06:40:11", "1", "1", "1", "133", "1", "2"], "0150": ["/", "3"], "0151": ["Ci\u1eddi7a", "V5 TRON-TIO2", "06:40:15", "290", "Gon", "33"], "0152": ["247/79", "06:40:18"], "0153": ["677/79", "12/600", "06:40:24"], "0154": ["Co.op", "06:40:31", "1"], "0155": ["Co.op", "0640:36"], "0156": ["Co.op", "06:40:41", "1"], "0157": ["3", "H7/VQ", "06:40:46", "X"], "0158": [], "0159": ["HTVQ", "06:40:51", "HIED", "G\u1ea6N 60 XE NH\u1eceI NH\u1ebeT KH\u00c1CH D\u1ecaP"], "0160": ["TOO IREN", "476/07/2"], "0161": ["CH\u01af\u01a0NG TR\u00ccNH 60 GI\u1ea6Y", "6", "HT/VIN", "18:30 TR\u1ea6N HT/7", "06:41:06"], "0162": ["Cogize", "06:41:06"], "0163": ["HT/V7QN", "06:41:1"], "0164": ["HG/VO", "LINI"], "0165": ["So", "607", "0", "10/7", "27770 20", "50", "1020", "194", "06:41:16", "K0\u00e1", "Tai", "C\u1ea9m alling", "/a", "1"], "0166": ["18/079", "06:41:18"], "0167": [], "0168": ["HG/79", "06:41:30"], "0169": ["LE/20/02", "06:41:37"], "0170": ["H7/V940"], "0171": [], "0172": [], "0173": ["191720", "06:42:00"], "0174": [], "0175": ["Co0p", "06:42:07"], "0176": [], "0177": ["H7/V940", "06:42:"], "0178": ["BCA ng\u00e0y 03/6/2014", "C\u00d4NG AN T\u1ec8NH AN GIANG", "C\u1ed8NG H\u00d2A X\u00e3 H\u1ed8I CH\u00da NGH\u0129a VI\u1ec6T", "NAM", "C\u01a0 QUAN THI H\u00c0NH \u00c1N H\u00ccNH", "\u0110\u1ed9c l\u1eadp - T\u1ef1 do - H\u1ea1ng", "108", "06/42:18", "5/0\u0110.TN", "S\u1ed1:05", "An giang, ng\u00e0y 10 th\u00e1ng 10 n\u0103m 2018", "NGUY\u1ebeT \u0110\u1ecaNH TRUY N\u0102M", "T\u00f4i: \u0110\u1ea1i t\u00e1 L\u00e2m Th\u00e0nh Sol", "Ch\u1ee9c v\u1ee5: Th\u1ee7 tr\u01b0\u1eddng C\u01a1 quan THAHS C\u00f4ng an t\u1ec9nh An Giang", "1", "C\u0103n c\u1ee9 Quy\u1ebft \u0111\u1ecbnh s\u1ed1: 12/2018/Q\u0110-CA ng\u00e0y 23/7/2", "C\u1ee7a P\u00f2a \u00e1n", "nh\u00e2n", "d\u00e2n huy\u1ec7n T\u1ecbnh Bi\u00ean, t\u1ec9nh An Giang v\u1ec1 vi\u1ec7c thi h\u00e0nh \u00e1n ph\u00fa", "T\u1ed5i", "V\u1edbi ng\u01b0\u1eddi b\u1ecb", "k\u1ebft \u00e1n Nguy\u1ec5n Ho\u00e0ng D\u0169ng dang \u0111\u01b0\u1ee3c t\u1ea1i ngo\u1ea1i", "C\u0103n c\u1ee9 V\u0103n b\u1ea3n s\u1ed1: 164/\u0110N-TA ng\u00e0y 20/8/2018 c\u1ee7a T\u00f2a \u00e1n nh\u00e2n d\u00e2n huy\u1ec7n", "T\u1ecbnh Bi\u00ean, An Giang v\u1ec1 vi\u1ec7c y\u00eau c\u1ea7u truy n\u00e3 \u0111\u1ed1i v\u1edbi ng\u01b0\u1eddi b\u1ecb k\u1ebft \u00e1n Nguy\u1ec5n", "Ho\u00e0ng D\u0169ng \u0111\u01b0\u1ee3c t\u1ea1i ngo\u1ea1i ch\u1ea5p h\u00e0nh \u00e1n ph\u1ea1t t\u1eeb \u0111\u00e3 b\u1ece tr\u1ed1n:", "C\u0103n c\u1ee9 \u0110i\u1ec1u 364 B\u1ed9 lu\u1eadt t\u1ed1 t\u1ee5ng h\u00ecnh s\u1ef1 n\u0103m 2015, s\u1eeda d\u1ed1i, b\u1ed1 sung n\u0103m", "2017, c\u00e1c \u0111i\u1ec1u 13, 15, 24, 32, 100 Lu\u1eadt thi h\u00e0nh \u00e1n h\u00ecnh s\u1ef1 n\u01b0\u1edbc CHXHCN Vi\u1ec7t", "Nam v\u00e0 \u0110i\u1ec1u 10 Th\u00f4ng t\u01b0 li\u00ean t\u1ecbch s\u1ed1: 13/2012/TTLT-BCA-BTP-VKSNDTC", "TANDTC ng\u00e0y 09/10/2012 c\u1ee7a B\u1ed9 C\u00f4ng", "B\u1ed1", "Vi\u00ean"], "0179": ["HG/V", "06:42:21"], "0180": [], "0181": ["Co.op cao", "06:42:32", "1"], "0182": ["Gi\u1eddi cu\u1ed9c cu\u1ed9c cu\u1ed9c cu\u1ed9c chu chu cung cu", "06:42:39", "23", "1"], "0183": ["H7/VINH", "06:42:44", "AN GIANG B\u00c1T QU\u1ea2 1", "NG\u01af\u1edcI \u0110", "\u0110\u00c1NH B\u00c0", "TANG", "TR\u1ea6N THUA B\u0102NG TI\u1ec0N"], "0184": [], "0185": ["HI/79", "06:42:54", "3", "SAY", "2000"], "0186": ["47/07940", "06:42:57", "33", "290"], "0187": ["H7/7079:00", "06:43:00", "500000"], "0188": ["H7/VQHN", "06:43:04"], "0189": ["HODING", "06:48:08"], "0190": ["HT.79", "06:48:10"], "0191": ["HG/79", "06:48"], "0192": ["Cogize", "06:43:22"], "0193": ["HT/79", "06:43:29", "\u0110\u1ed2NG D", "U/01", "gi\u1edd", "THAM GIA \u0110\u00c1NH B\u1ea0C \u0102N TI\u1ec0N T\u1ea0I HUY\u1ec6N TR\u00c1NG BOM"], "0194": ["H3/79", "06:43:32"], "0195": ["Gi\u1eddi gian", "06:48:37", "SUBSCRIBED"], "0196": ["Cogon ao", "06:43:44"], "0197": ["Cogon cao", "06:48:51", "1"], "0198": [], "0199": ["B\u00c1N H\u00c0NG"], "0200": ["HIVI", "06:44:03", "1003", "1005", "SCOTT", "SCOT", "100", "009", "SCO", "JLIOO", "3000", "04:"], "0201": [], "0202": ["1", "HG/V", "1", "06:44:09", "10", "Gia", "1", "Fi", "1", "300", "1", "3", "1"], "0203": ["HT/794", "06:4", "1", "SCOT", "1", "1103", "1", "JIOQ", "11009", "11005", "E", "3", "1", "11009", "109", "11009", "1009", "E", "11635", "gi\u1edd", "11009", "CIOQ", "SCOTT", "1", "11033", "900"], "0204": [], "0205": ["HT/V9H", "06:44:18"], "0206": ["H7/V940", "06:44:21"], "0207": ["H7/079", "06:44:20"], "0208": ["H7/17941", "06:44:30"], "0209": ["H7/0794", "06:44"], "0210": ["H7/17940", "06:44:31"], "0211": ["H7/07940", "06:44:18"], "0212": ["HG/V", "1883", "Tido"], "0213": [], "0214": ["H7/V94", "06:44:46"], "0215": [], "0216": ["XI", "HG/V", "016:4433", "217", "0", "1"], "0217": ["HT/V", "06:45:01", "16/0:0"], "0218": ["Giang", "06:45:07"], "0219": ["Giang", "06/45:07"], "0220": ["Cogi7: cao", "06:45:14", "1", "1"], "0221": ["Cogon 2020", "06:45:19"], "0222": ["3", "H7/70700", "06:45:20", "VORLD HEADQUARTER", "FORD", "GAMER"], "0223": ["6000 6000 00,000", "06:45:33"], "0224": ["17"], "0225": ["H7/VINH", "06:45:40"], "0226": ["Co0p", "0645:44", "Gord", "Y"], "0227": ["29 0", "13"], "0228": ["596", "06:45", "57"], "0229": ["C1077 Qu\u1ea3", "06:45:54", "Gord"], "0230": ["6/7/79", "06:45:58"], "0231": ["677/079", "06:46:04"], "0232": ["06:46:08"], "0233": ["0", "4/72", "G7P", "06:46:15"], "0234": ["GI\u0110", "06:46:18"], "0235": [], "0236": ["HTWIND", "06:46:28", "CONG", "NH\u1ec0N", "ROBOT", "TR\u1ee2 KI\u1ec0M", "THOA", "NUI"], "0237": [], "0238": ["H7/29", "06:46:38"], "0239": ["HT/7", "06:46:46"], "0240": ["H7/V940", "06:46:45"], "0241": [], "0242": ["41/10", "06:46:55"], "0243": ["H7/07Qu\u1ea3", "06:47:06"], "0244": ["H7/0794", "06:47:04"], "0245": ["H7/029", "06:47:06"], "0246": ["HT/79", "06:47:11"], "0247": ["HI/79", "06:47:19"], "0248": ["Li\u00ean", "06:47:22"], "0249": ["HT/V794", "06:47:"], "0250": ["GI\u1edcI V\u00c0", "CCL", "06/47/30", "Li\u00ean", "11", "00.000", "THE EE", "1", "CH\u1ec0", "NGU"], "0251": [], "0252": ["H7/794", "NH:06:4", "47:39", "1"], "0253": ["18", "Gi\u1eddi cho chu chu chu cu", "CHI\u1ebeN", "18", "06:4"], "0254": ["H7/V940", "06:47:4", "SPI"], "0255": ["H7/V940", "06:47:50", "T CRA", "Tuu mut chung", "PH\u00da (CF TI\u1ebeN - H\u1ea2I C\u1ea8M)"], "0256": ["Gi\u1eddi T\u00e2y", "0647:56", "c"], "0257": ["Cogo2ao", "06:48:08", "1"], "0258": ["Cigi7 cao", "06:48:06", "1"], "0259": ["Cogitan", "06:48:10", "1", "Nui"], "0260": ["Ng\u00e0y 20", "06:48:13", "\u0110\u00c1C"], "0261": ["Cogize", "0648:17", "2", "1", "1", "\u00c1c", "\u0110I\u1ec0U"], "0262": ["P.A", "Hau Thanh thu cao", "9", "06:48:21", "111,", "1", "777", "1", "1"], "0263": ["1"], "0264": ["HT/V940", "06:48:23"], "0265": ["A", "HT/D79", "06:48:2", "1"], "0266": ["61077900", "06/8:29"], "0267": ["H7/V7940", "06:48:3"], "0268": ["HT/70", "06:48:37", "F21", "TT F.", "1"], "0269": ["Cogize", "06:48:42"], "0270": ["G/T/V94", "064843"], "0271": ["H\u1ed3/79", "06:48:48"], "0272": ["HO\u00c0NG"], "0273": ["1", "Cogon9up", "0648:51", "771"], "0274": ["G\u00f2m 70", "06:48:55"], "0275": ["HO\u00c0N", "16:49408"], "0276": ["HT/0790"], "0277": ["H7/V7940", "06:49:1", "SCEN", "PORO", "1"], "0278": ["HG/79", "06:49:"], "0279": ["H7/VIN", "06:49:21"], "0280": ["HG/79", "06:49:28"], "0281": ["HT/0"], "0282": ["H7/17941", "06:49:38", "COURNOYER", "NICOLA", "\u0110\u1ed2NG S\u00c1NG L\u1ea6P IGLOOFES"], "0283": ["H7/17941", "06:49:"], "0284": ["HG/V7", "06:49:49"], "0285": ["HT/V79", "06:49:48"], "0286": ["HG/79", "06:49", "AURENT", "MAURENA", "NG\u01af\u1edcI THAM D\u1ef0"], "0287": ["H7/07900", "06:49:59"], "0288": ["00/5", "GLO", "HT/17941", "06:50:06"], "0289": ["Cogitar", "06:50:09"], "0290": ["Commerce", "06:50:16", "1"], "0291": ["Cogiza", "06:50:23", "1"], "0292": ["H7/V940", "06:50:2"], "0293": ["H7/079", "06:50:33", "1", "TI\u1ec0N", "NH\u1ea0C", "DOC KINH T", "SINH BAN", "NUI"], "0294": ["6/0/7940", "06:50:37"], "0295": ["HG/79", "06:50:40"], "0296": ["H7/0790", "06:50:40"], "0297": [], "0298": ["HG/V", "1", "06:50:59"], "0299": [], "0300": ["H7/07941", "06:51:09"], "0301": ["H7/707Q", "06:51:"], "0302": ["H7/17941", "06:51"], "0303": [], "0304": ["H7/079", "06:51:"], "0305": ["0", "HD", "06:51:35"], "0306": ["H\u1ed3 17", "06:51939"], "0307": [], "0308": ["HG/7", "06/51", "7", "8"], "0309": [], "0310": [], "0311": ["HT/079", "06:52:00"], "0312": ["14/5/079", "06:52"], "0313": ["H7/079", "06:52:06"], "0314": ["HG7/79", "06:52"], "0315": ["HT/79", "06:52:16", "10", "Sai", "200", "12/07/2020"], "0316": ["4/7/022", "06:52:20", "Sai"], "0317": ["LHO/V", "06:52-28"], "0318": ["Gi\u1eddi 7, Qn", "06:52:24"], "0319": ["HO/70", "06:52:20"], "0320": ["HG/79", "06:52:30"], "0321": ["1", "15", "ng\u00e0y", "06:52:35", "7", "9", "4", "7 2", "1"], "0322": ["HG/V9", "06:52:40"], "0323": ["14/07/79", "06:52:42"], "0324": ["HT/V79", "06:524"], "0325": [], "0326": [], "0327": [], "0328": ["HG/79", "06:54:25", "90,7", "T\u1ed5ng c\u1ea9m c\u1ea3", "71", "Thu\u1ef7 thu\u1eadn thu\u1ef7 thu\u1ef7 thu\u1ef7 thu\u1ef7"], "0329": ["1", "F", "36", "11747 2000", "1", "06:54:26", "1", "L\u00ea M\u00f4i", "DUA THUY\u1ec0N TRUY\u1ec0N THONG N\u0102M 2023", "Thanh 1, P.000 Thang Nam"], "0330": [], "0331": ["Ci\u1eddi7a", "06:54:32", "1", "DOAN VDU", "DO\u00c0N VDV", "DO\u00c0N VDV", "HUY\u1ec6N N\u0102M NH\u00daN, T\u1ec8NH LAI CH\u00c2U", "HUY\u1ec6N THAN VY\u1ec0N, T\u1ec8NH LAI CH\u1ea2", "T\u1ed4NG LAY, T\u1ec8NH \u0110I\u1ec6N BI\u1ec2N", "EN", "HOI:", "\u0110\u1ed2NG", "QUYNH D", "THUY", "NHA", "\u0110UA"], "0332": ["H5/070", "06:54:34", "RMY"], "0333": ["Co.op commerce", "06:54:36", "T\u00caN TI\u1ec0N", "SHAMIN", "P.C\u1ea9m TP.", "P.0+"], "0334": ["HG/79", "06:5438"], "0335": [], "0336": ["CON CH\u01af\u01a0NG TH\u00c0NH QU\u1ea6Y", "Coang cao", "18:30 TR\u00caN", "06:5444"], "0337": ["CH\u01af\u01a0NG TR\u00ccNH 60 GI\u1ea6Y", "18:30 TR\u00caN"], "0338": ["Thanh", "HG/79", "06:5456", "Trinh", "/2"], "0339": ["610707900", "06:54:57", "1"], "0340": ["Con", "15/00", "Cogize", "10.5.1", "06:55:02", "SUBSCRIBED"], "0341": ["HT/79", "06:55:08"], "0342": ["1017/20", "06:55:15"], "0343": ["Co0m", "06:55:19"], "0344": ["Ho/2900", "06:55:20"], "0345": [], "0346": ["HT/V9HD", "07:01:46", "1", "0", "giay", "0", "VII2"], "0347": ["6/7/79", "07:01:52", "0", "1", "1", "00", "771:"], "0348": ["H7/7941", "07401:50"], "0349": ["HU7IZOND", "07:00:14", "115", "gia", "XII"], "0350": ["HG/79", "07:00:19", "1/1", "60", "77/2"], "0351": ["HG79", "07:00:4"], "0352": ["H67079", "07:00:3"], "0353": ["HIV9", "07:00:1", "TRUNG T\u00c2M TIN T\u1ee8C", "\u0110\u00c0I TRUY\u1ec0N H\u00ccNH TH\u00c0NH PH\u1ed0 H\u1ed2 CH\u00cdMINH"]}