{"0001": ["HG/V", "8929", "gia", "V"], "0002": ["28/5/V", "18,29:59", "1", "Gia,", "7772"], "0003": ["HG/V", "80401", "100", "H\u1ed2NG LOAN", "H\u1ea2I TRI\u1ec0U", "7", "1", "1"], "0004": ["H7/V", "1", "1"], "0005": ["HG/V", "18:30:30:30"], "0006": ["HG\u00c0Y", "18:30:14"], "0007": ["G/7/7/00", "18:30:16"], "0008": [], "0009": ["HE/V", "18:30:26", "6", "1010", "9"], "0010": ["171", "13", "HG/V77 HD", "774 - 1000", "18:30:31", "149", "1", "13"], "0011": ["HIA", "1", "7", "HT/V77 HD", "194 - 1000", "18:30:91", "164", "0"], "0012": ["6/7177/20", "18:30:36", "CH\u00cdNH", "2", "SILVER SPIRIT", "T\u1ed5 17/10", "130 033:"], "0013": ["HTV"], "0014": ["18/5/V", "18-3046", "1", "1"], "0015": ["HG\u00c0Y", "18-30:59", "1"], "0016": ["18/570", "18-30:54", "1"], "0017": ["HG\u00c0Y", "1831:0", "0"], "0018": ["HG/V", "1"], "0019": ["677/07/700", "18:31:15", "\u0110\u00d4N"], "0020": ["HT/V7/HD", "18:31:22"], "0021": ["12/000", "Tu\u1eadn An", "\u0110i An", "\u0110I\u1ec0M \u0110\u1ea6U", "G/7/7/00", "BI\u1ec2N HO\u00c1", "18:31:27", "Ho Chi", "Minh City", "Di An", "C\u00c1NG HKQT", "LONG TH\u00c0NH", "2", "\u0110I\u1ec0M CU\u1ed0I", "H\u1ed3 Tr\u1ea7n", "33", "94", "1"], "0022": ["Thu\u1eadn An", "TI\u1ebeP THEO TR\u1ea6N C\u1ea2NG TR\u1ea6N", "G/7/7/7/00", "HTV v\u00f4 B\u1ea1n Ch\u1ea3o Xu\u00e2n", "18:31:32", "Ho Chi", "\u0110i\u1ec1minh City", "\u0110I\u1ec0M C\u01af\u1edc", "GAU - 604n M\u00f5 R\u1ed9ng", "M\u00c1T C\u1ea2", "T\u1eeb Km16-800 \u0111\u1ebfn", "-400", "GIAI \u0110OAN", "AN XE", "GIAH \u0110OAN", "HT", "Ba Ria", "H\u1ed3 Tr\u00e0", "33", "9", "1"], "0023": ["TI\u1ebeP THEO TR\u1ea6N GI\u1edcI", "40/7/2000", "HTV v\u00f4 B\u1ea1n Ch\u1ea3o Xu\u00e2n", "18:31:35", "\u0110ai", "60"], "0024": ["6/7077:0", "18:31:38", "D Food", "GIANH C\u1ee7a MOI CIZA PHIM"], "0025": [], "0026": [], "0027": [], "0028": ["HG/V7", "18:3149"], "0029": [], "0030": [], "0031": ["6/7077/00", "18:32:01", "1"], "0032": ["HG/V", "18:32:0"], "0033": ["HG/V", "18:32:10", "Tui", "1", "1"], "0034": ["HG/V"], "0035": ["HG/V", "1"], "0036": ["28/5/V", "1"], "0037": ["HG\u00c0Y", "18-32-29"], "0038": ["HT/V77 HD", "18:32:34", "Saining", "P.Commin", "n\u0103m", "EN", "TRONG", "TH\u00c0NH", "T\u1ee8C HO\u00c1", "METRO", "209"], "0039": ["HG\u00c0Y", "18:32:30", "NH", "EN", "T\u1ef0C HO\u00c1", "METRO", "TRONG"], "0040": ["HG/V", "18:32:4", "JID"], "0041": ["HG/V", "18:39"], "0042": ["HG\u00c0Y", "18:32:4"], "0043": ["G/707/700", "18:32:49", "SCC", "SUBSCRIBED"], "0044": ["HG/V", "18:32:54"], "0045": ["GI\u1edcI TH\u1eca TI\u1ebeN TI\u1ebeN TI\u1ebeN TI\u1ebeN TI\u1ebeN TI\u1ebeN TI\u1ebeN TI\u1ebeN TINH", "1832:59"], "0046": ["HG\u00c0Y", "18:33:03", "10"], "0047": ["JICA"], "0048": ["G/7/7/7/00", "18:33:14", "1", "1960 PHAT:", "NOISHING", "TATSUYA A", "MASUZAWA", "K\u1ea6Y D\u1ef0NG TUY\u1ebeN METRO", "GI\u00c1M \u0110\u1ed0C D\u1ef0 \u00c1", "TR\u1ea6N LI\u1ec0N DANH"], "0049": ["HG/C7", "18:33:11"], "0050": ["HG\u1edcI V\u00c0", "/ CJE", "11"], "0051": ["HG/V", "2"], "0052": ["HG/V", "1", "1"], "0053": [], "0054": ["HG7", "Bi", "18:3304", "1", "23", "To\u00e1c ng\u00e2y", "1", "F2", "T\u1ed5ng ch\u1ec9", "PP", "13", "Tang 1", "Nin ed", "1.3", "T\u1ed4N"], "0055": ["L", "HG/V7", "KH\u00c1CH", "18:33:47", "Ca", "1", "67/4", "E", "Phg", "1", "19,9.0", "1", "1", "Fox", "1", "03", "DT", "1", "9", "402,", "33 mi", "TAI", "a", "GO", "1020", "CHI"], "0056": ["2", "0"], "0057": ["18/5/00", "18:33:58", "P. 6", "\u0110\u1ed2NG GIA", "FLAT PRICE", "30.000", ":"], "0058": ["H\u00e0ng li\u00ean", "Online", "T\u00ean", "HG/V7", "18:34:04", "THAI", "21", "1"], "0059": ["HG\u00c0Y", "18:34:10", "Gang", "Gang", "T\u1ed4 10", "01"], "0060": ["HG\u00c0Y", "8:34:", "2", "Sa", "1", "711"], "0061": ["477/7/700 13", "18:34:17", "K\u00caNH SI\u1ec0U T", "672017"], "0062": ["6/707/700", "18:34:19", "K\u00caNH SI\u1ec0U TH\u1eca", "67017", "NGUY", "HOI", "TNG TH\u00da", "QU\u1ea6N PH\u00da NHU\u1ea6N", "MART RA", "TRUONG", "TPHCA"], "0063": ["HG/V", "18:342", "3000", "E33", "1"], "0064": ["HO\u00c0NG TH\u1eca TRUNG", "18:34:25", "10", "Saigon"], "0065": ["59", "T\u1ed4 H\u1edcI", "Vegetable", "18:34-28", "1"], "0066": ["47707/00", "18:34:31", "BINH SI\u1ec0U", "gi\u1edd"], "0067": [], "0068": ["HG/V7", "18:34:34:", "1", "1"], "0069": ["G\u00f2m 1", "18:34 40", "0:11", "1", "1"], "0070": ["HG\u00c0Y", "18:34-48", "1", "1", "1", "Tay (x La", "LAN", "620"], "0071": ["HG/V"], "0072": ["HEZV"], "0073": ["HG/V", "18:35:01", "1", "Vin", "22/177272", "A", "14/2020", "11", "1", "1"], "0074": ["HT/V7 Tap", "1", "18:35:03", "1", "04/07", "T\u00ca", "5", "623"], "0075": ["11", "2", "1", "757", "HO\u00c0NG TH\u1edcI", "64 - 1000", "18:35:07", "1143", "1", "3", "SANG", "T\u1ea6U BI\u1ec0N", "HANG :", "DON"], "0076": [], "0077": ["1", "1"], "0078": ["1", "Gia", "HG/V", "18:35:21", "FF", "SCA"], "0079": ["HT/V/700", "18/05:24", "13", "17"], "0080": ["HG\u00f2n", "18:35:20"], "0081": ["03", "91"], "0082": ["HG\u00c0Y", "18:35:32"], "0083": ["677/77/10", "18:35:37", "60", "UNVERS"], "0084": ["677/077:0", "18:35:39", "De 3", "SILVER SPIRIT", "T\u1ed5 3/07", "13B-013N", "THAOC"], "0085": ["43B-051.69"], "0086": ["LIE", "2", "FE", "1", "\u0110IR", "D", "6", "23", "1"], "0087": ["HG/V", "18:35:5"], "0088": ["1", "11", "1"], "0089": ["LHE/V", "18:35:51", "2"], "0090": ["28/570", "18-36:04", "4"], "0091": ["16/570", "18-86:10", "1"], "0092": ["HG/V", "18936"], "0093": ["HGD", "18:36/28", "VI\u1ebeNG", "C\u00d4NG", "\u0110\u1ed0C \u0110\u00c1O", "UC V", "C\u1eecA NG\u01af D\u00c2N \u0110\u00c1T \u0110\u1ed0"], "0094": [], "0095": ["HG/V", "18:36:36"], "0096": [], "0097": ["HEIVA", "18:36:42"], "0098": ["HG/V", "18:36:46"], "0099": ["1", "HGL7", "18:36:47", "10"], "0100": ["HT/V7nd", "18:36:48"], "0101": ["HO/V", "18:36:56"], "0102": ["1", "HG/V", "18:36:56"], "0103": ["HG/V", "18:36:57", "3/5000", "Tang commerce"], "0104": ["1", "HG7V", "18:37:03"], "0105": [], "0106": ["HG/V", "18:37:09", "3"], "0107": ["HG/V72", "18:37:12"], "0108": ["28/5/V", "1"], "0109": ["HG/V", "1", "1"], "0110": ["HG/V", "1"], "0111": ["HG/V"], "0112": ["HG/V", "18:37:40", "1"], "0113": ["HGI\u1edcI", "18:37:8"], "0114": ["HG/V", "18:37:08"], "0115": ["HGLV", "18:37:51"], "0116": ["HG/V", "H", "HUMILONG 5:", "18:37:57", "Anh", "1"], "0117": ["HG/V", "18:38:00", "1", "P", "A", "V", "ph\u00fat", "1", "1"], "0118": [], "0119": ["18/070", "18:38:10"], "0120": ["HG/V", "18:38:16"], "0121": ["HG/V", "18:38:2"], "0122": ["H5/V", "18:38:24"], "0123": [], "0124": ["GHE70", "TV V", "v\u00e0 B\u1ea1n Ch\u00e0o X\u00e3", "18:38:38"], "0125": ["HG/VA", "18:38:39"], "0126": ["HG/V", "V CIB", "gi\u1ea7y", "VII"], "0127": ["H5/V"], "0128": ["HG/VA", "8.40"], "0129": ["HG/V", "18:40:28"], "0130": ["G/707/7/00", "18:40:30", "10.5"], "0131": ["HG/V", "18:40:32", "4,00", "332", "Th\u1ee3 c\u1ed9", "3:5:3", "10/00", "93", "VINH PHANGLE", "coVigan"], "0132": ["71.1", "HO\u00c0N", "18:40:341", "WASHINGTON", "YU", "YING", "PUBLIC CHARTER", "SCHOOL"], "0133": ["gi\u1edd", "18:40:36"], "0134": ["HE7V", "18:40:4"], "0135": ["HG/V/ZH", "18:40:49"], "0136": ["HG/V", "18:40:4"], "0137": [], "0138": ["HGLV", "18:40:5"], "0139": [], "0140": ["HG\u00c0Y 7 H\u00c0", "18:41:04"], "0141": ["HGI\u1edcI T\u1ed4NG TI\u1ec0N TI\u1ec0N TI\u1ebeN TI\u1ebeN TI\u1ebeN TI\u1ebeN TI\u1ebeN TI\u1ebeN TI\u1ebeN TI\u1ebeN TI\u1ebeN TIN", "18:4161", "1", "Ca"], "0142": ["G/70/7/00", "18:41:14", "1"], "0143": ["16/5/00", "18:41:18", "0", "1"], "0144": ["28/5/07", "18-41:22", "MEHI", "NAM", "RANG", "CON"], "0145": ["HG/V", "Con4 3:4", "10"], "0146": ["HG/V", "094034", "67"], "0147": [], "0148": ["HEIV", "1", "1"], "0149": ["HG/V", "1"], "0150": ["14/5/07", "18:41:49", "9", "200", "1"], "0151": ["HEIVE", "18:41:50", "hoga", "Romi", "1", "\u0111\u1ea1i"], "0152": ["HG/V", "18:41:55", "Ta", "200"], "0153": [], "0154": [], "0155": [], "0156": ["HGA", "gi\u1ea5y", "77"], "0157": ["1", "0", "6", "LID"], "0158": ["18/07/7", "18:49:20", "1", "giay", "777"], "0159": ["HO\u00c0NG TH\u1eca TR\u1ecaNH", "18:42:27"], "0160": ["nev", "HG\u00c0Y", "18:42:3:", "a week ofrunning and", "XU H\u01af\u1edcNG L\u00dd", "T\u1ed4NG", "LEN", "DU LICH", "NGO)", "TONGT", "NGO"], "0161": ["Sharjah, United Arab Emirates", "HG/V/700", "18:42:39", "This", "aims to recreate", "safar", "barka", "pa", "Africa", "habitats fo", "found i", "SUBSCRIBED"], "0162": ["reate", "aimstorecr", "N", "t", "This", "safari", "bar", "1", "tsfound", "habita", "at"], "0163": ["HG\u00c0Y", "18:42:46"], "0164": ["6/707/700", "18:42:50", "f 800", "Alt covers an area off", "necta", "cares", "ho", "and hosts", "themed", "viron", "ni", "nV", "er", "1110"], "0165": ["6/7077/n0", "18:42:56", "S\u1ed1", "GIAN", "10"], "0166": ["HG/V", "18:43:02"], "0167": ["HG/V7 THD", "18:43:09", "KYRICOS", "MIA", "CHUY\u1ec0N GIA T", "DU LICH"], "0168": ["QUO", "\u0110aew", "HG\u00c0Y", "Lave", "18:43:12"], "0169": ["HG/V7", "18:43:15"], "0170": ["QU", "onew", "ave", "HG/V", "18:48:20"], "0171": ["onew", "avel", "HGD7", "18:43:22", "After a", "quick stop f", "forap", "picnic", "an", "oasis", "mini"], "0172": [], "0173": [], "0174": [], "0175": ["TH\u1edcI V\u00c0", "18:43", "R\u01af\u1edcU VANG", "KH\u00c1CH"], "0176": ["HG/V", "18:43:50", "6"], "0177": [], "0178": ["HG/V", "18:44404"], "0179": ["HO\u00c0NG TH\u1eca TR\u1ecaNH", "18:44:11"], "0180": ["HG/V", "H\u0110", "18:44:1"], "0181": ["HG\u00c0Y"], "0182": ["H7/V"], "0183": ["H777/V7"], "0184": ["477/07/700", "18:47:32", "THED"], "0185": ["HT/V7/A\u0110", "18:47:39", "THEO"], "0186": ["GI\u1edcI TH\u1eca HO\u00c0NG TR\u1ecaNH", "18:47:45"], "0187": ["28/5/0", "18:47:52", "1"], "0188": ["HG/V", "118/077:0", "1"], "0189": [], "0190": ["H\u1ed3 V7 N\u1ed9i", "18/48:04"], "0191": ["6/7077:0", "18:48:11"], "0192": [], "0193": ["677/077/20", "18:48:20", "Ni\u00ean c\u1ea3"], "0194": ["HG/V", "18:48:25"], "0195": ["HO\u00c0NG TH\u1edcI TI\u1ebeN TI\u1ebeN TI\u1ebeN TI\u1ebeN TI\u1ebeN TI\u1ebeN TI\u1ebeN TI\u1ebeN TINH", "18:48:30", "1"], "0196": ["G/7/777/20", "18:48:92", "a"], "0197": ["477/07/700", "18:48:36"], "0198": [], "0199": ["1"], "0200": ["HO\u00c0NG TH\u1edcI TI\u1ebeN TH\u1edcI", "18:48:55", "63", "9"], "0201": ["477/07/7n0", "18:48:59", "Gi", "235.7", "6", "A/NOB", "GIAO", "NAN", "K\u1ebeT XE K\u1ebeO D\u00c0"], "0202": ["HO\u00c0NG TR\u1ecaNH", "18:49:08", "102.200", "51G", "2195", "NAN GIAO", "TRUNG", "KET XE K\u1ebeO D\u00c2N"], "0203": ["G/707/n0", "18:49:06", "M\u1ed9i - m\u1ed9i", "DANGER", "60K", "235.73"], "0204": ["6/7077/00", "18:49:08", "332", "60K", "235.73"], "0205": ["4/7077/00", "18:49:12", "60K", "235.73"], "0206": [], "0207": ["6/7077/n0", "18:49:20", "82"], "0208": [], "0209": [], "0210": ["HT/V77 HD", "18:49:31"], "0211": [], "0212": ["HGLV", "18-19", "2"], "0213": ["HG/V", "18:49:4", "1"], "0214": ["1.64", "12/501", "722220", "Th\u00e0nh to\u00e1n", "69.0", "Fino", "Thu\u1ef7 g\u00f2n"], "0215": ["HG/7:", "9/H\u0110", "18:49:58", "LIEN", "GIANG", "TREN", "CHA"], "0216": ["477/07/200", "h\u00e0o \u00e1", "18:50:02"], "0217": ["70/07", "HG/V", "HTV v\u00f4 B\u1ea1n Ch\u1ea3o Xu\u00e2n", "18:50:04", "Dicao", "18"], "0218": ["HG\u00c0Y", "18:50:09"], "0219": ["133", "6/707/700", "17/10/0860:11", "1", "72A-309:95"], "0220": ["HG/V7", "CHU PH\u1ed0", "18.50:16", "VFTHNIVIGN"], "0221": ["P.", "35/411", "Gian", "HG\u00c0Y", "18/50:22", "3"], "0222": ["HT/V7/HD", "18:50:25", "T\u00e2y"], "0223": ["0", "HGI\u1edcI", "CHE", "18:50:29", "Vicac", "Tin", "50", "g.3:", "6", "G\u00f2", "1"], "0224": ["GI\u1edcI TH\u1eca TI\u1ebeN TI\u1ebeN TI\u1ebeN TI\u1ebeN TI\u1ebeN TI\u1ebeN TI\u1ebeN TI\u1ebeN TI\u1ebeN TIN", "18:50:36", "VOI \u0110:"], "0225": ["HT/V/7", "18.50:4", "1", "a"], "0226": ["677/07/700", "18:50:46"], "0227": ["HT/V7/10", "18:50:59"], "0228": ["HEZV", "18.50:5", "T\u1ed4NG", "CH\u1ea2Y", "C\u01af B\u1ed0C", "NG\u00c0N", "TRONG KHU"], "0229": ["C\u1eec"], "0230": ["6/7077/n0", "18:51:04"], "0231": ["6/707/700", "18:51:11"], "0232": ["HG/V", "18:51:18", "Gia 11", "Tang comminh"], "0233": ["1", "HGAN", "18:51:20", "23"], "0234": ["24/0/V", "18:51:20"], "0235": ["CONTENSINE CARE UNIT", "TH\u1edc TH\u00c0M B\u1ec6NH", "T\u1ed5ng : Ch - b\u1ea3o", "13:125", "C\u1eecA S\u1ed0 1"], "0236": ["VM INICNOIVC CANE VINI", "HG/V7:0", "18:51:35", "GI\u1edc TH\u00c2M B\u1ec6NH", "Sang: 3 G\u00f2", "0-80", "C\u1eecA S\u1ed0 1", "Chi\u1ec1u: I An"], "0237": ["HG\u00c0Y", "18:51:4"], "0238": ["TI\u1ebeP THEO TR\u1ea6N TO\u00c0N", "HGIV", "HTV v\u00e0 B\u1ea1n Ch\u1ea3o Xu\u00e2n", "18:51:48", "Methano", "Methylalkoho", "CH, - OH", "11-23/24/25", "39/23/24/25", "S: 7-16-36/37-4", "Giftklasse:"], "0239": [], "0240": ["HG\u00c0Y", "HD", "18:51:55"], "0241": ["HG/V", "18:51:59", "13", "1"], "0242": ["HG/V", "18:52:08", "La", "200"], "0243": ["VM C/ Commerce", "18:52:10"], "0244": ["HG/V", "18-52", "Methang", "Methylalkoh", "CH, - OH", "TR: 11-23/24/25", "39/23/24/25", "S: 7-16-36/37", "Giftklass"], "0245": ["Methan", "N", "Methylalkoho", "CH, - OH", "11-23/24/25", "39/23/24/25", "S: 7-16-36/37-4", "Gift klasse:"], "0246": ["18:52:22"], "0247": ["HG/V", "CAP C\u1eecU", "VG 9-2 TC", "18:52:26", "152", "Thang cu\u1ed1c gia"], "0248": ["MINH CAP", "CHUNG S\u1ed0NG AN TO\u00c0N V\u01a0I \u0110\u1ea0I D\u1ecaCH COVID-1", "HG\u1edcI", "18:52:29", "5K", "HON"], "0249": ["CAP C\u1eecU", "gi\u1edd", "P:MICKG", "18:52:33", "6K"], "0250": ["HG/V", "18:52:33", "799", "0.50", "146/89 (106)", "30 0", "SUBSCRIBED"], "0251": ["G/7/7/00", "18:52:41", "198", "16", "1"], "0252": ["G/707/700", "18:52:44", "191", "16"], "0253": [], "0254": ["HO\u00c0NG", "18:58:58", "777"], "0255": ["59:02", "1", "1"], "0256": ["G\u00f2m 7", "18.59408", "Vincommin"], "0257": ["HG/V", "18:59:18", "NII", "10", "B\u1eca M\u00c1T 1", "PAKISTAN", "TREN", "QUC", "18", "11/000"], "0258": ["Fing"], "0259": ["HG/V", "18:59:20"], "0260": ["HG/V", "18:594", "1"], "0261": ["HG/V", "18:59:26"], "0262": ["HG/V", "GIA", "18:59"], "0263": ["t\u00ea", "3H", "1980", "HG/V", "41", "11 18:59:3", "511"], "0264": [], "0265": [], "0266": ["HG/V", "3", "giay", "11"], "0267": ["HG\u00c0Y", "18:59:40", "1", "60", "7772"], "0268": ["HG\u00c0Y", "18:49:38", "N\u00c0NG O", "TH\u1ee8C NG\u01af\u1edc", "TRONG", "GIU:", "NG", "CAO"], "0269": ["HG/V", "18:49:4"], "0270": ["HO\u00c0NG TH\u1edcI", "18:49:44"], "0271": ["HO\u00c0NG TH\u1edc", "18/19"], "0272": ["HG/V", "18:49:5:", "TD"], "0273": [], "0274": ["HG/V", "18:50:02"], "0275": ["HGLY", "18:50:05"], "0276": ["HG/V", "18.504"], "0277": ["HG/V7 HD", "18:50:14"], "0278": ["8.50"], "0279": ["HG/V7", "18:50:23"], "0280": ["H5/V", "18:50:23"], "0281": ["HG/V", "18:50:32"], "0282": ["GI\u1edcI GIAN"], "0283": ["G/G\u00f2y"], "0284": ["HT/V7:D", "18:50:47", "N\u01af\u1edcC C\u1ed8NG HOA X\u00e3 H\u1ed8I CH\u00da NGH\u1ec8A VI\u1ec6T NAM MU\u1ed0N N\u0102M", "Co"], "0285": ["HEIV", "18:50:50", "TH\u01af\u1edcNG N\u00d3NG", "B\u1ea0C LI\u1ec0U:", "L\u1ef0C L\u01af\u1ee2NG C\u00d4NG AN PH\u1ea2", "AN NHANH"], "0286": ["HG/V", "18:50:50"], "0287": ["1", "\u0110\u1ea1i"], "0288": ["477/07/700", "18:51:04", "P"], "0289": ["Vinoxuocal"], "0290": ["6/7007/00", "18:51:11"], "0291": ["G/7/77/20", "18:51:15", "Gia"], "0292": ["07"], "0293": [], "0294": ["CHEV", "13", "200"], "0295": [], "0296": ["HG/V", "18:51:36"], "0297": ["G/707/00", "18:51:38", "1"], "0298": [":0", "010"], "0299": ["H7/V7:D", "18.518", "7"], "0300": [], "0301": ["H7/V/HD", "18:51:54", "1", "T\u1eeb: 7"], "0302": ["CH/T/VA", "1922", "18:5158"], "0303": ["HO\u00c0NG TR\u1ecaNH", "18:52:08", "1", "1", "1", "1", "117:33", "3/111", "PGC", "1"], "0304": ["TI\u1ec0P THBO TR\u00caN CITY", "677/07/700", "C\u0110ER", "18:52:08", "C\u1ed8NG AN TP.HCM", "X\u1eec L", "G\u1ea6N 2.300 TR\u01af\u1edcNG H\u1ee2P XE KH\u00c1CH VI PH\u1ea0M"], "0305": ["10", "TIEP THEO TR\u00caN", "HP", "TS\u00c1C", "18:52:13", "Cin", "La", "2", "0", "Vi\u00ea"], "0306": ["MINH", "B\u00f2", "Vichoa", "1", "C\u00d4NG D\u00c0", "082066031773", "T\u00e2n \u0110\u00e0nh khu\u00ea", "2", "V\u00c0", "67 lac", "La 3ry", "Qu\u1ea3ng", "15,8", "Tao cua", "h\u0111", "T\u1ed9 L\u1eadp bi\u1ec3n Ph\u1ea3o t\u1ea1m gi\u1edd", "3370", "AGoo", "Ti\u1ec1n l\u0129nh A", "9066", "50 91,710", "072", "\u0110C - P.C", "VCAP", "Ni\u00ean t\u1ed5 chi\u1ec1u"], "0307": ["HE7V", "18:52:19"], "0308": ["G/707/700", "18:52:22", "1", "THACO", "SUBSCRIBED"], "0309": ["HG/V", "18:52:", "1", "3", "1", "11", "13", "3", "3", "13", "3", "3", "3", "3", "3", "3", "3", "3", "1", "1", "1", "3", "3", "2", "7", "3", "2", "3", "2", "2", "3", "3", "3"], "0310": ["HO/77 HO\u00c0NG", "18:52:29", "1"], "0311": ["GI\u1edcI GI\u1edcI TI\u1ebeN TI\u1ebeN TI\u1ebeN TI\u1ebeN TI\u1ebeN TI\u1ebeN TI\u1ebeN TI\u1ebeN TIN", "18:59:94", "1000h2", "OSANN", "T\u00ea c\u01b0\u1eddng n\u00e0y cao c\u1ea5p A", "Toa"], "0312": [], "0313": ["677077/00", "18:52:42", "Ca", "5000", "Minip commining the commerce"], "0314": ["HG/V", "18:52:49"], "0315": ["40", "G/707/700", "18:52:50", "18:3", "TOAN"], "0316": ["HG/V", "18:58:56"], "0317": ["HG/V", "18-58-59"], "0318": ["HG/V", "gi\u1ea7y", "XII"], "0319": ["HG/V", "03", "gi\u1ea7y", "X71"], "0320": ["HG\u00c0Y", "8:59:"], "0321": ["CV", "FIN", "AE"], "0322": ["NEW", "AP", "EA", "Vi", "9"], "0323": ["H7/V"], "0324": ["CHO\u00c0N", "Cii", "411"], "0325": ["HTV", "18:59:40", "1", "Gia", "0", "7712"], "0326": ["2", "2", "THE/177", "18:59:46", "77", "60", "777"], "0327": ["47707720", "18:48:29"], "0328": ["GNID", "HO7C77/AN", "18:48:32"], "0329": ["HO707/CO0", "09", "18:48:34", "11", "1", "11", "VQIPHO", "19"], "0330": ["6/570"], "0331": ["G/570"], "0332": ["HE7V"], "0333": ["6/070", "2", "1"], "0334": ["HO\u00c0NG TH\u1eca TI\u1ebeN", "3", "18:48:52", "TH\u1ea6N", "NH\u00c2N D\u00c2N"], "0335": ["H\u1ed3/V7/H\u00e0", "18:48:54", "NHAI", "DAI"], "0336": ["G/G/V", "18:48:59", "3", "1", "B\u1eca C\u00c1O", "HI", "H\u1ed2N"], "0337": ["771"], "0338": ["69007720", "18:49:09", "1"], "0339": ["6/017/20", "18:49:14", "\u0110..."], "0340": ["6/017/20", "18:49:14"], "0341": ["17/5707", "18:49:19", "7", "1", "a", "1", "1", "CAO"], "0342": ["LH/G/V"], "0343": ["HE70"], "0344": ["6/070", "10"], "0345": ["HG7"], "0346": ["CHIAU", "- DUNG CU Y T\u1ebe", "THANG - M\u00dd PH\u00c1M", "HT/V7", "18:50::18:50::18:50:18", "H CH\u00c0O"], "0347": ["CH\u00c2U", "- DUNG CU Y TH", "THANG - MY PH\u1ea8M", "HG/V7", "H\u0110", "18:50:32", "CH\u00c2U", "HI C"], "0348": ["G/G/V", "18:50:32", "1", "93"], "0349": [], "0350": ["H7/V7/HD", "QU\u1ea2 THU\u1ed0C MINH CH\u00c2U", "18:50:4", "DUNG CU T", "TH\u1ea0I", "CHUY\u1ec0N BAN L\u00dd:", "PH\u1ea2M CH\u00daC NANG - M\u00dd PH\u1ea8M", "MINH", "THU\u1ed0C MINH CH\u00c2U", "QU\u1ea6Y", "A", "TH CH\u1ea2", "CLEAP"], "0351": [], "0352": [], "0353": ["HG/V7", "THU\u1ed0C MINH CH\u00c2U", "18:50:53", "THU\u1ed0C MINH CH\u00c2U"], "0354": ["NGUY THU\u1ed0C MINH CH\u00c2U", "HO\u00c0NG", "18:504", "THU\u1ed0C MINH CH\u00c2U"], "0355": ["16/5707", "18:50:57"], "0356": ["HGZV", "18:51"], "0357": [], "0358": ["G\u00f2, 7 H\u00e0", "3", "P", "1", "Co.op commerce", "13/00"], "0359": [], "0360": [], "0361": [], "0362": ["a"], "0363": [], "0364": ["HG/V77", "18:57:35", "I\u1ec0N", "CHAY", "CHINH", "NAM"], "0365": ["HT/V77", "18:57:40"], "0366": ["HG/V7", "77/h", "18:57:44"], "0367": ["HT/V77H", "18:57:43", "Say"], "0368": ["HT/V77 AD", "18:57850", "Tai", "20"], "0369": ["HG/V77 HA", "18:57:53", "SAY"], "0370": ["H\u1ed3 V7 Th\u00e1", "18:57:57"], "0371": ["HG/V7", "17/H", "18:58:00"], "0372": ["HO\u00c0NG TH\u1eca", "18:58:08"], "0373": [], "0374": ["HO7/V7/HD", "18:58:10"], "0375": ["HT/V7/HD", "18:58:15", "FERNANDA", "MACIED", "V\u1ea6N \u0110\u1ed8NG VI\u1ec0N CH\u1ea0Y B\u1ed8 SI\u1ec0U T\u1ed0C NG\u01af\u1edcI BRAZIL"], "0376": ["HO/VINH", "18:58:17"], "0377": ["HG/V7", "18:58:11"], "0378": ["HG/V7", "18:58:20"], "0379": ["HO7/V7/HD", "18:58:22"], "0380": ["HT/V7/HD", "18:58:25"], "0381": ["HG/V77H", "18:58:23", "45", "2"], "0382": ["H\u1ed3/077", "18:58:30"], "0383": [], "0384": ["HO/V7/HD", "18:58:35"], "0385": ["HO\u00c0NG TH\u1edcI", "18:58:36"], "0386": ["472", "18:58:39"], "0387": ["47A", "18:58:40"], "0388": ["F/1", "472", "18:58:45"], "0389": ["HG/V", "18:58:50", "1"], "0390": ["HT/07/AD", "18:58:55", "1", "63A", "225.30", "ti\u1ec1n giang", "T\u1ea0I NAN GI\u1eeeA", "XE BEN", "T\u1ea0I TR\u1ea0M THU PH\u00cd CAO T\u1ed0C"], "0391": ["CJ007720", "18:58:59", "2270"], "0392": ["6/017/20", "18:59:00", "678"], "0393": ["HT/V77", "18:59:02"], "0394": ["HG/V77 HU", "18:59:03", "SUBSCRIBED"], "0395": ["HG/V7/HD", "18:59:07", "63A", "225.3e", "SUBSCRIBED"], "0396": ["HT/V7 ZHI", "18:59:10", "63A", "225.3"], "0397": ["HG7/V7/00", "18:59:10", "Coi", "Coan"], "0398": ["HOV", "18:59", "22536"], "0399": [], "0400": [], "0401": ["67017/200", "18:59:20"], "0402": ["HGL7", "10", "18.59:20", "63A", "225.36"], "0403": ["1", "HT/V77 HL", "18:59:22", "25"], "0404": [], "0405": ["6/07/7/20", "18:59:23", "QNH"], "0406": ["670707720", "18:59:24", "1", "1"], "0407": ["G\u00f2ng 1", "18:59:28"], "0408": ["HG/V2", "1", "771"], "0409": [], "0410": [], "0411": ["HG7", "1", "92", "777"], "0412": ["H\u1ed3 V77", "18:59:4"], "0413": ["HG\u00c0Y", "18:59:"], "0414": ["67017/20", "1849:50", "0", "94C", "056.00", "HINO", "14", "3", "17"], "0415": ["6/707/707/20", "1849:55", "Hyundan", "VINMOUSING", "4:31 3: XI", "3"], "0416": ["6/7077/20", "18:50:00"], "0417": [], "0418": ["G\u00f2 7/ 17/20", "18:50:08"], "0419": ["677/07/20", "18:50:10"], "0420": ["GI\u1edcI 7 / HD", "18:50:15"], "0421": ["gi\u1edd", "18:50:1"], "0422": ["HGD7", "18:50:2"], "0423": ["6/017/20", "18:50:28"], "0424": ["6/017/700", "18:50:25", "B\u00ccNH PH\u1ee8C", "NGAN", "CONTAINER", "QU\u1ed0C L\u1ed8 14 K\u1ebeT XE H\u01a0N 2KM"], "0425": ["H0/07/7", "18:50:30", "13", "BINH", "CONTAINER", "XE G", "ph\u01b0\u1eddng", "QU\u1ed0C L\u1ed8 14 K\u1ebeT XE H\u01a0N 2KM"], "0426": ["1", "407077HD", "2", "18:50:31"], "0427": ["10/202/H00", "18.50:3", "CA"], "0428": ["H\u1ed3 V7 7", "18:50:36", "53", "303"], "0429": ["G\u00f2 7/07/20", "18:50:37", "THANH H\u00c0I", "516-91026"], "0430": ["31 2/7", "HT/71", "18:50:39"], "0431": ["T\u1ed5 65 18", "HO/V/TH", "18:50:39"], "0432": ["GI\u1edcI 7 A0", "18:50:40"], "0433": ["HG/V"], "0434": ["16/070", "1", "1"], "0435": ["6/070"], "0436": ["HO7 07/20", "18:51:45"], "0437": ["HT/V77", "18:51:48"], "0438": ["H7/07/10", "18:51:53"], "0439": ["Gi\u1eddi 7", "18:51:55", "NGGG V\u00c0 2", "6.7"], "0440": ["HG/V7/HD", "18:51858"], "0441": ["HT/V7/HD", "18:52:03"], "0442": ["HG/V7:", "17/H", "18:52:08"], "0443": ["H07/77", "18:52:08"], "0444": [], "0445": ["677/07/700", "18:52:13"], "0446": ["H\u1ed3/07/H\u00e0", "18:52:19"], "0447": ["HG/V7", "18:52:18", "/4"], "0448": ["HT/V7 HA", "18:52:23"], "0449": ["196707", "18:52:23"], "0450": ["HO7V", "7"], "0451": ["HT/V", "72"], "0452": ["HT/V", "7/H0", "Gia", "771"], "0453": ["H75/V", "GI\u0110", "11"], "0454": [], "0455": ["HG\u00c0Y", "17/H", "18:52:"], "0456": ["6767077HD", "18:52:44"], "0457": ["PH\u1ea2 \u0110I T\u1ed4NG N\u00c0Y ALIA"], "0458": ["HG/V", "18:52:58"], "0459": ["HG\u1edc 7", "1"], "0460": [], "0461": [], "0462": [], "0463": ["6/017/00", "18:52:58", "C"], "0464": ["67017/00", "18:53:02", "233", "ng\u00e0y"], "0465": [], "0466": [], "0467": [], "0468": ["6/5707", "53:1"], "0469": ["16/070", "7/CH\u0110", "18:53"], "0470": ["186/000", "18:5391"], "0471": ["H\u1ed3 V77", "18:53:19"], "0472": ["Gi\u1edd 7/0", "18:53:21", "6"], "0473": ["677077/000", "18:53:22"], "0474": [], "0475": ["LH/G/V", "18:59400", "0", "772"], "0476": ["HT/V", "7/H0", "gi\u1ea7y", "1"], "0477": ["H672", "HD", "8.59"], "0478": ["6/7/07/20", "18:59:18"], "0479": ["677/07/20", "18:59:22", "QANTAS H\u1eceNG:", "M\u00c1Y BAY C\u1eecA H\u00c0NG GIA", "\u0110\u00d4NG C", "C\u01a0 KHI \u0110ANG BAY", "GI\u1eeeA BI\u1ebeN"], "0480": ["HG/V7/HD", "18:59:27"], "0481": ["HT/V7/HD", "18:59:32", "SUBSCRIBED"], "0482": ["HG/V7/HD", "18:59:37"], "0483": ["H\u1ed3/V7/H\u00e0", "18:59:37"], "0484": ["HO7V77HD", "18:59:42"], "0485": ["HGV", "7/H0", "gi\u00e2y", "1"], "0486": ["HTZ", "7/H0", "gi\u00e2y", "7"], "0487": ["HG/V", "7/H0", "gi\u00e2y", "17"], "0488": [], "0489": ["HGD7", "19:00:00"]}