{"0001": ["CJ0079:0", "06:29:44", "gi", "IA"], "0002": ["HI/79", "06:29:4", "6", "3", "6", "1/1", "160", "7/72"], "0003": ["H7/079 HD", "06:29:53", "60", "H\u1ea2I TRI\u1ec0U", "M\u1ef8 KH\u1ece", "gi\u1ea5y", "771", "1"], "0004": ["HGI7900", "06:29:59", "33", "Gian"], "0005": ["H079:0", "06:29:59"], "0006": ["HG/V", "06:30:00"], "0007": [], "0008": ["HG/79", "06:30:09", "V CH\u00cdNH", "Tang 1, Thanh 1, Thanh Trinh Thuy Hinh Trinh Thung Huy Ninh Thung Ninh Trinh Thung Huy Ninh Thu Trang Huy Ninh", "1", "K\u1ebeT C", "C\u1ea6U", "CHUNG C\u1eec", "Toi 0"], "0009": ["16/07/7", "Tan", "1", "1", "CA", "1", "1", "10", "1", "0", "10", "13"], "0010": ["HG/79", "06:30:1", "1", "1882"], "0011": ["H\u1ed3 79", "06:30:20", "Di u", "1822", "T\u1ed4 88", "Ti\u1ec1n \u1ee7i", "1000", "3.321", "Thu cua", "\u00d4 3 00"], "0012": ["47/79", "V.GID", "630:24"], "0013": ["H7/079 HD", "06:30:36", "gi\u1ea5y", "777"], "0014": ["H7/7079:00", "06:30:37", "gi\u1ea5y", "777"], "0015": ["HO/VINH", "T\u01af LI\u1ec6U", "06:3043"], "0016": ["1"], "0017": ["HT/V9HD", "T\u01af LI\u1ec6U", "06:30:51", "1"], "0018": [], "0019": ["1", "18/079", "SHITTLY", "T\u01af LI\u1ec6U", "06:30:57", "EL", "5", "S\u0129, 11", "KHU V\u1ef0C PH\u00c1T H\u1ed2 S\u01a0N", "AA", "HUY \u0110\u1ed8NG TR\u00ca RA L\u1ee8P 1", "N\u0102M H\u1eccC 2020-2021", "H\u1eccC SINH TR\u00c1NH CH\u01a0N", "S\u1ed0 KHU V\u1ef0C N\u00c0Y", "103", "1"], "0020": [], "0021": ["LHE707", "T\u01af LI\u1ec6U", "Poon\u01b0\u1ee3c", "06:31:04", "1", "PHI\u1ebeU", "X\u00e3 H\u1ed9i Ch\u00fa Ngh\u0129", "\u0110\u1ecdc l\u1eadp", "T\u1ef1 \u0111o", "K\u00dd H\u1eccC L\u1ee8P B\u00c1N", "19C 2020", "5.3", "202", "L\u00ca QU\u00dd", "T\u1ed4", "1"], "0022": ["202677779", "GAO", "2022-", "SINH", "NH", "1", "GH\u1ed0I", "T\u01af LI\u1ec6U", "06:31:08"], "0023": [], "0024": ["HT/V79HD", "06:31:15"], "0025": ["H\u1ed3/V79hd", "06:31:22", "1"], "0026": ["SAIGONFOURMST HOSPITALITY COLLEGE", "6/007/2000", "06:31:29"], "0027": ["T\u1ed5 3", "3.", "A.030"], "0028": ["6/007 Sau", "06:31:36", "Vind Dearc laulies and gentlend", "1"], "0029": ["6/007900", "06:31:40"], "0030": ["6/7/079", "06:31:4", "\u0110 T\u00caN"], "0031": ["16/5707", "06:31:49", "T\u1ed4 TH\u00c0NH", "SUBSCURED"], "0032": ["Gi\u1edd 7 Sap", "06:31:58", "SUBSCRIBED"], "0033": [], "0034": ["HT/V79", "06:31:58"], "0035": ["3", "1", "TI\u1ebeC -", "54.50", "7", "107", "HT/791", "1", "4:", "06:32:01", "05"], "0036": [], "0037": ["CJ0079:00", "06:32:05", "3", "3"], "0038": ["67017910", "06:32:12"], "0039": [], "0040": ["HGU7", "06:32:26", "300"], "0041": ["H7/079HD", "\u0110\u1ea0I", "06:32:24", "JIE", "th", "1", "7", "1"], "0042": ["HT/V79", "06:32:28"], "0043": ["6/007900", "06:32:32", "HUNGVUONGTE"], "0044": ["Gi\u1edd 7 giao", "06:32:33"], "0045": ["Gi\u1eddi Vino", "06:32:36"], "0046": ["677079H0", "06:32:40"], "0047": ["H6/V", "06:3246", "M/J0", "VM"], "0048": ["9HD", "HG/V", "06:32:53"], "0049": ["T\u1ed4NG S\u1ea2N", "LII", "Thanh", "Gi\u1edd 7 Sau", "06:32:57", "GNII", "vincommerce", "TININ", "TI3MID", "Giang", "13"], "0050": ["T\u1ea0I PH\u1ea2I A"], "0051": [], "0052": ["6/0079", "06:33:09"], "0053": ["Thanh thi", "Tin e", "SEED", "T\u1ed4 88 H\u1ed2", "TEDINNAN", "HGAV", "06:333", "3", "Vitting 18/000 18/2020", "10", "1"], "0054": ["HT/079H1", "T\u00caN TH\u1eca 06:33:16"], "0055": ["16/0707", "06:33:20"], "0056": ["HG/V9HD", "06:33:21", "ng\u00e0y"], "0057": ["39", "18/000"], "0058": ["HG/7", "Tang 1, Toan"], "0059": ["HT/079HD", "06:33:32"], "0060": ["H7/79/00", "06:33:38", "3/000", "vincommerce", "(BINH)", "9"], "0061": ["CJ007900", "06:33:41", "Tilli - Van", "THERKER"], "0062": [], "0063": [], "0064": ["H\u1ed2/70", "GI\u0110", "06:33:5", "19/08:3", "10", "Gia"], "0065": ["The 11 00/16-2010", "THEI ITTITTLING"], "0066": ["HO79", "06:33:56", "18/08/08/2020 - THANH THANH THI\u1ec6N THUY THU THU TI\u1ebeN THU THU TI\u1ebeN THU THU HANH NHANH NHANH NHI\u1ec6N THI\u1ec6N THU THUY THUY THUY THUY THU", "82"], "0067": ["6/017900", "06:33:58"], "0068": ["677/079n0", "06:34:05"], "0069": [], "0070": ["6/07079H0", "06:3496", "NHI\u1ec0U LAO", "THEM", "HU/ONG", "LUZON", "V\u1edcI \u0110\u1ec0 XU\u1ea4T GI\u1ea2M N\u0102M \u0110\u00d3NG BHXH"], "0071": ["HG/V79HN", "06:34:19"], "0072": ["Ng\u00e0y 2", "6.9", "G", "19", "10", "19", "10", "3 4", "3.", "10:00", "10", "1", "63", "1", "4.000 00.000", "06:34:20", "59", "T\u1ed5ng Qn", "6.09", "Day", "19499", "19", "3/09", "349", "19", "03:49", "9", "T\u1ef1", "4", "02", "402.3", "10", "1", "7", "900", "2", "6", "G", "3", "3", "99", "10", "3", "17 P.93", "99/09", "Tao", "3", "1", "G", "4", "P.6", "03", "C", "29", "09,54"], "0073": ["\u0110\u1ea1i 2", "6.3", "0.09", "5.3", "6", "0", "8", "Gia", "00", "L\u1ed9 C3", "7", "9/000790", "6", "Q4/0709", "T\u1ed5 Qu", "99", "33", "Coi", "010", "03", "1", "9/09", "Tine", "3/090", "1/89/189", "19/09", "19", "QU", "5", "19", "600", "GCA.3", "10", "1", "CT", "10", "0.8", "7", "03", "G\u1ecdi", "G", "3", "01", "014", "99", "189", "1393", "19", "19/04", "Thu\u1ef7", "3", "3", "Q", ".3", "06", "08", "C1", "C\u1ea9m", "19", "Co", "19,1"], "0074": ["67017900", "06:34:32", "111"], "0075": ["P.C\u1ea9m Thu\u1ef7", "1", "HG/794", "06:34:3", "1", "99", "Q"], "0076": [], "0077": [], "0078": ["HGL7", "06:34:49", "10"], "0079": ["19", "H7/07040", "1", "1"], "0080": ["Tinh/ E", "Kinh gia: Bao", "2021", "C\u1ed8NG HO\u00c1 X\u00e3 H\u1ed8I CH\u00da NGH\u1ecaA VI\u1ec6T", "\u0110\u1ed9c l\u1eadp - T\u1ef1 do - H\u1ea1nh ph\u00fac", "H\u1ecd v\u00e0 t\u00ean (1): Niqtuy\u1ebfn - Ph\u00fa : Mu\u1ef7", "c\u1ea5p ng\u00e0y 15 th\u00e1ng", "M\u00c0 S\u1ed0 BHXH:", "099542.8736 70", "TP. Vinh bi\u1ec7t, \u0110id Ni\u00ean", "GI\u1ea6Y \u00daY QUY\u1ec0N", "S\u1ed1 CMND c\u1ea9n cu\u1ed1c c\u00f4ng d\u00e2n/ S\u1ed1 H\u1ed9 chi\u1ec1u- O3/474 H/ CD H", "pit.044 1", "Do C\u1ee5c Cau P C\u1ea9t", "ng\u00e0y", "S\u1ed1 \u0111i\u1ec7n tho\u1ea1i \u0111i \u0111\u1ed9ng (2)", "\u0110\u1ecba ch\u1ec9 li\u00ean h\u1ec7 (3)", "C\u1ea7n c\u1ee9 B\u1ed9 lu\u1eadt D\u00e2n s\u1ef1 n\u0103m 2015:", "C\u1ea9n c\u1ee9 v\u00e0o c\u00e1c v\u1ea7n b\u00e1n ph\u00e1p lu\u1eadt hi\u1ec7n h\u00e0nh", "N\u1ed9i \u0111ung y\u00eau c\u1ea7u gi\u1ea3i quy\u1ebft (5)", "H\u00f4m nay, ng\u00e0y 14 th\u00e1ng 03 n\u0103m 2023, t\u1ea1i tr\u1ee5 s\u1ed1 UBND ph\u01b0\u1eddng Ninh", "\u0110BHXH m\u1ed9t l\u1ea7n", "\u0110L\u01b0\u01a1ng h\u01b0u Th\u1eddi \u0111i\u1ec1m h\u01b0\u1edbng t\u1eeb th\u00e1ng", "ch\u00fang t\u1ed3i g\u1ed3m c\u00f3:", "-L\u00fd \u0111o n\u1ed9p ch\u1eadm (6):", "L. B\u00ean \u1ee7y quy\u1ec1n (B\u00ean A):", "Tr\u1ef1 c\u1ea5p m\u1ed9t l\u1ea7n \u0111\u1ec1 \u0111i n\u01b0\u1edbc ngo\u00e0i \u0111\u1ecbnh c\u01b0", "DChuy\u1ec1n n\u01a1i b\u01b0\u1edbng (ch\u1edd h\u01b0\u1eddng) l\u01b0\u01a1ng h\u01b0u, tr\u1ee3 c\u1ea5p BHXH t\u1eeb th\u00e1ng", "T\u1ed5ng L\u00ea V\u0103n QUANG, Sinh n\u0103m: 1971", "D\u01b0\u1eddng l\u1ea1i l\u01b0\u01a1ng h\u01b0u/tr\u1ee3 c\u1ea5p BHXH t\u1eeb th\u00e1ng", "CMND/CCCD s\u1ed1: 037071003972 c\u1ea5p ng\u00e0y 25/04/2021 t\u1ea1i C\u1ee5c c\u00e1nh s\u1eaft", "Nh\u1eadn l\u01b0\u01a1ng h\u01b0u/tr\u1ee3 c\u1ea5p BHXH c\u1ee7a nh\u1eefng th\u00e1ng ch\u01b0a nh\u1eadn", "Th\u01b0\u1eddng tr\u00fa t\u1ea1i: ph\u1ed1 An H\u00f2a, ph\u01b0\u1eddng Ninh Phong, TP Ninh B\u00ecnh, t\u1ec9nh Ninh", "Y\u00eau c\u1ea7u kh\u00e1c (T)", "\u0110\u1ecba ch\u1ec9 nh\u1eadn l\u01b0\u01a1ng h\u01b0u/tr\u1ef1 c\u1ea5p BHXH/n\u01a1i c\u01b0 tr\u00fa m\u01a1i (8)", "11. B\u00ean \u0111\u01b0\u1ee3c \u1ee7y quy\u1ec1n (B\u00ean B):", "D Qua t\u1ed5 ch\u1ee9c d\u1ecbch v\u1ee5 BHXH", "Nguy\u1ec5n Th\u1ecb Th\u1ee5y, sinh n\u0103m 1974", "S\u1ed1 t\u00e0i kho\u1ea3n", "Ch\u00ed nh\u00e1nh Th\u1ecb Ni\u00ean b\u00ecnh", "CCD s\u1ed1 037174004133 do C\u1ee5c c\u1ea3nh s\u00e1t c\u1ea5p 25/04/2021", "N\u01a1i \u0111\u00e1ng k\u1ef9 KCB", "T\u1edd quan BHXH", "O T\u1ea1i c\u01a1 0", "Nguy\u1ec5n Ti\u1ec7n Huy", "H\u00ecnh th\u1ee9c nh\u1eadn ti\u1ec1n l\u01b0\u01a1ng b\u01b0u/tr\u1ee3 c\u1ea5p BHXH (9)", "\u0110\u1ecba ch\u1ec9: ph\u1ed1 An H\u00f2a, ph\u01b0\u1eddng Ninh Phong, TP. Ninh B\u00ecnh, t\u1ec9nh Ninh B\u00ecnh", "T\u1ef1 ch\u1ecbu tr\u00e1ch nhi\u00ean", "nh\u1eadn ti\u1ec1n b\u00e0o hi\u1ebfm x\u00e3 h\u1ed9i (\u0111\u00f3ng t\u1ef1 nguy\u1ec7n)", "Quy\u1ec1n n\u00e0y trong t\u1ec9nh tr\u1ea1ng", "Ori\u1ec1n m\u1eb7t", "Nguy\u1ec1n: B\u00e0ng v\u1ea5n b\u00e1n n\u00e0y, b\u00ean A \u1ee7y quy\u1ec1n cho b\u00ean B", "N03/2023 \u0111\u1ebfn khi th\u1ef1c hi\u1ec7n xong c\u00f4ng vinh", "s\u0129 \u0111\u1ed1i v\u1edbi vi\u1ec7t", "Ng\u00e0y \u0111\u1ee9ng \u0111\u1ed1ng BHXH t\u1ef1 nguy\u1ec7n t\u1ed1i kh\u00f4", "T\u00f4i cam k\u1ebft trong th\u1eddi gian 12 th\u00e1ng k\u1ebf t\u1eeb ng\u00e0y", "s\u1ed1i quan h\u1ec7 gi\u1eefa ng\u01b0\u1eddi \u1ee7y quy\u1ec1n v\u00e0 ng\u01b0\u1eddi \u0111\u01b0\u1ee3c \u1ee7y quy\u1ec1n: l\u00e0 v\u1ee3", "T\u00e2m \u00e1p", "Ch\u00fa TK:"], "0081": ["Trans 1 4. CJ017 : CJ017 : 10", "06:34:57", "C\u00d4NG H\u1eceA X\u00e3 H\u1eceI CH\u1ec8 NGH\u00c0 VI\u00caN", "2", "1", "B\u1ea2O HI\u1ebeM X\u00e3 H\u1ed8I", "SO", "L\u00ca V\u0102N QUANG", "S\u1ed1 s\u1ed1: 3713010417"], "0082": ["Hu/Vong", "OCUA", "0693458", "6", "1", "GIA", "Toi"], "0083": ["1", "10/000", "06:35:04", "SIK"], "0084": ["47/079H0", "06:35:04", "1", "Ji", "01", "1", "1", "2", "3", "1", "1", "65783", "53573"], "0085": ["D\u1ecbch V\u1ef1", "157 KHU 13/04", "10139.11", "Sp rammer", "th\u00f4ng tin", "1635\u1eca CHUY\u1ebeN \u0110\u1ecaA B\u00c0N H\u01af\u1edcNG L\u01af\u01a0NG H\u01afU", "TR\u1ee2 C\u1ea8P BHXH", "Gi\u1ea3i quy\u1ebft chuy\u1ec1n h\u01b0\u1eddng sang \u0111\u1ecba b\u00e0n kh\u00e1c \u0111\u1ed1i v\u1edbi", "ng\u01b0\u1eddi \u0111ang h\u01b0\u1eddng l\u01b0\u01a1ng h\u01b0u, tr\u1ee3 c\u1ea5p BHXH h\u00e0ng", "ap h\u00e0ng", "th\u00e1ng v\u00e0 ng\u01b0\u1eddi ch\u1edd h\u01b0\u1eddng l\u01b0\u01a1ng h\u01b0u, tr\u1ee3 c", "th\u00e0ng", "\u1eca639\u1eca THAY \u0110\u1ed4I H\u00ccNH TH\u1ee8C L\u0129NH HO\u1eb6C TH\u00d4NG", "TIN NG\u01af\u1edcI H\u01af\u1edcNG CH\u1ebe \u0110\u1ed8 BHXH", "Ng\u01b0\u1eddi h\u01b0\u1eddng \u0129nh ch\u1ebf \u0111\u1ed9 BHXH b\u00e0ng ti\u1ec1n m\u1eb7t", "chuy\u1ebfn sang l\u0129nh b\u00e0ng t\u1ea3i kho\u1ea3n c\u1ea3 nh\u00e2n v\u00e0 n\u1ed9i", "ho\u1eb7c thay \u0111\u1ed5i th\u00f4ng tin ng\u01b0\u1eddi h\u01b0\u1eddng", "\u0110\u0102NG K\u00dd T\u00c0I KHO\u00c1N CHO CON", "\u0110\u0103ng k\u1ef9 t\u00e0i kho\u00e1n giao d\u1ecbch di\u1ec7n t\u1eeb cho con", "NGO7AJ C\u00c1P L\u1ea0I S\u1ed0 BHXH KH\u00d4NG THAY \u0110\u1ed4I", "TH\u1ed0NG TIN", "S\u1ed1 BHXH kh\u00f4ng thay \u0111\u1ed5i th\u00f4ng t\u00ednh", "C\u1ea9p", "1608AJ C\u00c1P L\u1ea0I S\u1ed0 BHXH DO THAY \u0110\u1ed4I T\u1eca", "TIN", "Ti\u1ec1m x\u00e3 h\u1ed9i do thay \u0111\u1ed5i th\u1eddi", "T\u1ea1i s\u1ed1 B\u00e0o hi\u1ec7n", "C\u1ea5p", "1652\u1eca \u1ee7y QUY\u1ec0N L\u0129nh THAY C\u00c1C CH\u1ebe \u0110", "TR\u1ee2 C\u00c1P TH\u00c1T NGHI\u1ec6P", "\u0111\u00f4 BHXH,", "T\u1ed5ng cuy\u1ebfn t\u1ec9nh thay c\u00e1c"], "0086": ["LHOV", "06:35:1", "1", "1", "33", "17/004", "NA"], "0087": ["40179", "+ HD", "06:35:11"], "0088": ["GI\u1edcI79:0", "06:35:18"], "0089": ["06:35:23"], "0090": ["Gi\u1eddi79:0", "06:35:26"], "0091": ["H\u1ed3 79", "06:35:38", "NH\u1eeeNG", "GUONG", "NH\u00c2N", "C\u1eecU NG\u01af\u1edcI G\u1eb6P N\u1ea0N TR\u1ec0N BI\u1ec2N"], "0092": [], "0093": ["HG/794", "06:35:37"], "0094": ["H7/7940", "06:35:42"], "0095": ["H\u1ed3 7/91", "06:35:4"], "0096": ["61007900", "06:35:49"], "0097": ["6/007940", "06:35:51", "3"], "0098": ["HG/79", "06:35:53"], "0099": ["HT/V79H", "06:36:00"], "0100": ["G\u00f2ng 17", "CH\u1eca", "06:36:03"], "0101": ["61007900", "3.NB", "06:36:09"], "0102": ["HT/V79HD", "2.5000 H", "06:36:13"], "0103": ["Gi\u1eddi79:0", "06:36:19"], "0104": ["Gi\u1eddi Vong", "06:36:23"], "0105": ["677/7900", "06:36:24", "6", "1", "4", ":", "13"], "0106": ["HGI79ND", "06:36:29"], "0107": ["H767 V\u00c0", "16:364", "gios", "063"], "0108": ["HE7V", "06:36:36"], "0109": [], "0110": ["3", "V\u00e3ng \u1ea1. Vi t\u1ed5 ch\u1ee9c Saigon Children s c\u1ed5", "Tr\u1ee5 S\u1ed1 Ch\u00ednh t\u1ea1i UNITED KINGDOM cho", "n\u00ean Ban T\u1ed5 Ch\u1ee9c \u0111ang g\u1eedi c\u00e1c ho\u1ea1t", "\u0111\u1ed9ng tr\u00ean \u1ee9ng d\u1ee5ng Telegram v\u00ec \u1ee9ng", "d\u1ee5ng n\u00e0y c\u00f3 t\u00ednh b\u1ea3o m\u1eadt cao v\u00e0 ph\u00fa h\u1ee3p", "v\u1edbi c\u00f4ng vi\u1ec7c vi c\u00f3 th\u1ec1 ho\u1ea1t \u0111\u1ed9ng Group", "tr\u00ean 200.000 ng\u01b0\u1eddi giao di\u1ec7n r\u1ea5t \u0111\u01a1n", "gi\u1ea3n v\u00e0 g\u1ecdn g\u00e0ng, Kh\u00f4ng bi\u1ebft b\u1ea1n \u0111\u00e3 c\u1ed5", "s\u1eafn \u1ee9ng d\u1ee5ng n\u00e0y tr\u1ec1n \u0111i\u1ec1n tho\u1ea1i ch\u01b0a \u1ea1\u00f5", "10:36:3", "D\u1ea1 e c\u00f3 r\u1ed5i a", "3", "B\u1ea1n k\u1ebft b\u1ea1n v\u1edbi minh \u0111\u1ec3 minh h\u1ed3 tr\u1ee3", "b\u1ea1n ho\u00e0n t\u1ea5t th\u00fa t\u1ee5c h\u1ed3 s\u01a1 H\u1ed9i Vi\u00ean", "Thi\u1ec7n Nguy\u1ec5n nh\u00e9"], "0111": ["TP. PH\u1ea2, TPA/SCH S\u1ed1 2.", "ng\u00e0y", "H\u1ecdc Th/ Ph\u00fa H\u00e0 N\u1ed9i", "T\u1ed5 1 Th\u00e0nh Ph\u1ea3nh Th\u00e0nh", "08/420"], "0112": ["CJ0179", "06:36:49", "10/000", "3:33:3"], "0113": ["HT/V9HL", "06:38:42"], "0114": [], "0115": ["18/707", "06:38:54", "1", "1", "10", "1", "10", "1", "1", "1", "Th\u1eddi", "1", "87", "2 C:", "1", "2", "T\u1ed5i", "21", "1", "7"], "0116": ["1", "HT/7980", "06:39", "13.7", "63", "6", "1", "X"], "0117": ["H\u1ed3 79", "06:39:06"], "0118": [], "0119": ["Ho7/79", "06:39:1"], "0120": ["HG/79", "06:39:19", "3", "1020", "1", "Fa", "1", "18", "1", "1", "1", "91", "TOCE", "1", "1"], "0121": ["HT/V9HD", "06:39:23"], "0122": [], "0123": ["H5/0794", "06:39:29"], "0124": ["77571", "0", "06:39:36"], "0125": ["HG/V79", "672", "06:39:39"], "0126": [], "0127": ["HT/790", "06:39:49", "GIANG:", "TIEN", "\u0110UOI", "V\u00e0o:", "M\u1ed8T NG\u01af\u1edcI PH\u1ea2I \u0110I C\u1ea8P C\u1eec"], "0128": ["HGL7", "06:39:54", "1234"], "0129": ["H\u1ed2/V79H", "06:39:59"], "0130": ["Gi\u1eddi79:0", "06:40:02"], "0131": ["HG/V9", "06:40:09"], "0132": [], "0133": ["Gi\u1edd 79:0", "06:40:19"], "0134": ["6/017900", "06:40:26"], "0135": ["6/017900", "06:40:29"], "0136": ["15/077/079", "DIAN TOAN", "T\u00ca H\u00c0NH P.IN", "60C", "496.11", "09", "D"], "0137": [], "0138": ["HG79", "06/10:46"], "0139": ["HGI7900", "06:40:5:"], "0140": [], "0141": ["F/A", "06:41:02"], "0142": ["HG/V79H", "0641:04", "1"], "0143": ["06:41:09"], "0144": ["9/HD", "16/57/170", "06:41:15"], "0145": ["HG/79", "06:41:18", "th\u00e0nh ph\u1ed1 vinh", "C\u00d4NG A", "V\u00d4NG 1", "TAI", "KI\u1ec0N", "\u1ed4T", "CHO", "1", "\u0110", "NONGE", "\u0110\u1ed8 0", "C\u1ed0N"], "0146": ["HG792", "Vining", "KI\u1ec0N", "NOI", "PH\u00c1T HI\u1ec6N M\u1ee8C VI PH\u1ea0M CAO K\u00dd L\u00daC"], "0147": ["HG/V9H", "06:41:28"], "0148": ["40/79", "0634"], "0149": ["HT/V9HL"], "0150": ["HG/791", "06:41:38"], "0151": ["HG/V"], "0152": ["HG7/79", "06:4"], "0153": ["HG/V9", "06:418"], "0154": ["HG/791", "Bang", "C32", "ng\u00e0y"], "0155": ["HG/794", "06:42:08", "33:", "1393", "1990"], "0156": ["HG/79", "06:42:09", "1"], "0157": ["677/079:00", "0642:15"], "0158": ["Gi\u1eddi79n0", "06:42:22"], "0159": ["P. CC\u1ea9m b\u1ea1n", "V\u00e0ng 9. Tr\u01b0\u1edbc khi b\u1eaft \u0111\u1ea7u c\u00f4ng vi\u1ec7c.", "minh s\u1ed1 t\u01b0 v\u1ea5n c\u1ee5 th\u1ec3 cho b\u1ea1n hi\u1ec1u n\u1ed9i", "\u0111ung c\u00f4ng vi\u1ec7c c\u00f4ng nh\u01b0 quy\u1ec1n l\u1ee3i b\u1ea1n", "s\u1ed1 nh\u1eadn \u0111\u01b0\u1ee3c khi \u0111\u1ed3ng h\u00e0nh c\u0169ng T\u1ed5", "ch\u1ee9c thi\u1ec7n nguy\u1ec7n Saigon Children", "Trong khi nghe minh t\u01b0 v\u1ea5n b\u1ea1n vui l\u00f2ng", "th\u1ea3 tim \u0111\u1ec3 minh hi\u1ec3u b\u1ea1n \u0111ang quan t\u00e2m", "Sau khi minh t\u01b0 v\u1ea5n xong n\u1ebfu ch\u01b0a hi\u1ec1u", "vui l\u00f2ng h\u1ed3i l\u1ea1i minh, Xin c\u1ea9m \u01a1n", "B\u1ea1n c\u1ed5 \u0111ang r\u00e0nh \u0111\u1ec1 nghe minh t\u01b0 v\u1ea5n", "c\u1ef1 th\u1ec3 c\u00f4ng vi\u1ec7c v\u00e0 quy\u1ec1n l\u1ee3i khi b\u1ea1n", "\u0111\u1ed3ng h\u00e0nh c\u0169ng T\u1ed5 ch\u1ee9c thi\u1ec7n nguy\u1ec7n", "Saigon Children s kh\u00f4ng \u1ea1", "D\u1ea1 v\u00e0ng \u1ea1", "N\u00e0y gi\u1edd em ch\u1ea1y tr\u1ea7n \u0111\u01b0\u1eddng", "B\u00e2y gi\u1edd e r\u00e0nh v\u00e0 t\u1eadp trung \u1ea1"], "0160": ["TP T", "3", "V\u00e3ng \u1ea1. Vi t\u1ed5 ch\u1ee9c Saigon Children s c\u1ed5", "Tr\u1ee5 S\u1ed1 Ch\u00ednh t\u1ea1i UNITED KINGDOM cho", "n\u00ean Ban T\u1ed5 Ch\u1ee9c \u0111ang g\u1eedi c\u00e1c ho\u1ea1t", "\u0111\u1ed9ng tr\u00ean \u1ee9ng d\u1ee5ng Telegram v\u00ec \u1ee9ng", "d\u1ee5ng n\u00e0y c\u00f3 t\u00ednh b\u00e0o m\u1eadt cao v\u00e0 ph\u00fa h\u1ee3p", "v\u1edbi c\u1ed9ng vi\u1ec7c v\u00ec c\u00f3 th\u1ec3 ho\u1ea1t \u0111\u1ed9ng Group", "tr\u00ean 200.000 ng\u01b0\u1eddi giao di\u1ec7n r\u1ea5t \u0111\u01a1n", "gi\u1ea3n v\u00e0 g\u1ecdn g\u00e0ng, Kh\u00f4ng bi\u1ebft b\u1ea1n \u0111\u00e3 c\u00f3", "s\u1eafn \u1ee9ng d\u1ee5ng n\u00e0y tr\u00ean \u0111i\u1ec1n tho\u1ea1i ch\u01b0a \u1ea1\u00f5", "D\u1ea1 e c\u00f3 r\u1ed3i a", "1", "B\u1ea1n k\u1ebft b\u1ea1n v\u1edbi minh \u0111\u1ec3 minh h\u1ed3 tr\u1ee3", "b\u1ea1n ho\u00e0n t\u1ea5t th\u1ee7 t\u1ee5c h\u1ed3 s\u01a1 H\u1ed9i Vi\u00ean", "Thi\u1ec7n Nguy\u1ec7n nh\u00e1"], "0161": ["Ch\u00fa 8/12, P.000 TP. QNH TP. C\u1ea9m Thu\u1ef7", "TP QNOBNG NHAD, VA-DON MICH 5", "Q. 1900", "PH\u1ea0M TH\u00c0NH TR\u1ecaNH", "P.CO", "T\u1ed5 Th\u00e0nh H\u00ecnh B\u00ecnh C\u1ee7a Tranh", "1953", "NG\u00c0Y 18/18", "Th\u00e0nh H\u00e0nh Ph\u00fa N\u1ed9i V\u00e2y P.C\u1ea3"], "0162": ["19 - 83", "\u0110\u1ea1i 1", "This photo is from a post", "Colop commerce", "TR\u00c0 EM S\u1ea2I G\u1ed2N", "06:42/42", "Tebruary 26 at 9:03 AM", "do Like", "O Comment", "A Share", "89, Write a comment", "200000", "SUBSCRIBED"], "0163": ["9 Q Search Facebook", "89", "8", "TR\u00ca EM S\u00c0I G\u00f2N", "6/7/70", "LI\u0110", "06:42:44", "006", "\u0111\u1ed9 Like", "O Comm", "\u0110 Share", "Q 0090", "Write a commerce", "NHIN L\u1ea0I K\u1ebeT OU\u1ea2", "\u0110\u1ed9 V\u0103n Th\u1ecb N\u00e0y", "Toa Ninh Nam", "Scc all photos", "Photos", "Viewmore comments", "TR\u00ca BM S\u00c1I GON", "Feb/uary 26 - 8-18:AM", "Ch\u00fang t\u1ed1i r\u1ea5t may m\u1ea7n co m\u1ed9t h\u1ed9i \u0111\u1ed3ng xu\u1ea5t s\u1eafc v\u1edbi nh\u1eefng k\u1ef9 m\u1ed9ng v\u00e0 kinh nghi\u1ec1m \u0111o dang, H\u1ecd", "c\u1ed9ng nhau \u0111\u00f4ng g\u1ed1p v\u00e0o nh\u1eefng th\u00e0y d\u1ed1i t\u00edch c\u1ef1c cho tr\u1ea3 em kh\u00f4 kh\u00e2n \u1edf Vi\u1ec7t Nam, T\u1ea5t c\u1ea3 \u1ee7y vi\u00ean", "trong h\u1ed9i \u0111\u1ed3ng \u0111\u1ec1u ho\u00e1t \u0111\u1ed1ng d\u01b0\u1eddi t\u01b0 c\u00e1ch l\u00e0 t\u1ec9nh nguy\u1ec7n vi\u1ec7n v\u00e0 kh\u00f4ng h\u1ec7 nh\u1eadn b\u1ea5t k\u1ef9 kho\u00e1n", "l\u01b0\u01a1ng n\u00e0o", "C\u00fac \u1ee7y vi\u00ean c\u00f4 tr\u00e1ch nhi\u00eam qu\u1ea7n l\u1ef9 salgonchildien, \u0111\u00e2m b\u1ea3o m\u1ecdi c\u00f4ng vi\u00eac su\u00f4n s\u1ed1 v\u00e0 ph\u00fac vu lci", "c\u1ed9ng \u0111\u1ed3ng nh\u01b0 m\u1ee5c ti\u1ec1u \u0111\u00e3 \u0111\u1eb7t ra", "Ngo\u00e0i ra, c\u00e1c \u1ee7y vi\u00ean \u0111\u1ea7m b\u1ea3o ho\u1ea1t \u0111\u1ed3ng c\u1ee7a caigonchild.", "Seemore"], "0164": ["30", "82 saigonchildren", "Can T\u1ed5a Y\u00eau Th\u01b0\u1eddng", "4 HO\u1ea0T \u0110\u1ed8NG", "SAIGON CHILL", "LDRE", "C\u00e1c H\u1ed9i Vi\u00ean c\u1ea9n", "ho\u00e0n th\u00e0nh khi", "tham gia Group.1", "HO\u00c0N TH\u00c0NH 8 HO\u1ea0T D\u1ed8NG LI\u1ec0N TI\u1ebeP QU\u00dd H\u1ed8I VI\u00caN S\u1ec0 NH\u1ea6N TH\u1ec0M", "100.000 VND TR\u00cdCH T\u1eeb QU\u1ef8 T\u1eec THI\u1ec6N SAIGON CHILDRENS"], "0165": [], "0166": ["A MISSIO", "00", "s disadvantaged"], "0167": ["H7/7/V", "0643", "TH\u1edcI GIAN NG\u1ea0T \u0110\u00d4", "09:00 - 20:30", "1", "SAIGONCHILDREN K", "94", "VI\u1ec0N \u0110\u00c1 TH\u1eca", "QU\u00dd H\u1ed2I V\u00c0", "M\u1eeeNG Q", "TI\u1ec0N NGUY\u1ec0N", "GIA GROUPHOI T", "SAIGON CHILDREN", "TRONG Q", "TO\u00c1T \u0110\u1ed8", "THAM GIA C\u00c1C HO\u00c1N", "P NEU C\u00d3 B\u00c1T K\u00dd", "GROUP", "T\u01afC TR\u1ef0CT", "Seemore of Saigon Children: Charity co"], "0168": ["6007900", "06:43:07", "000000"], "0169": ["HG/V79", "06:43an"], "0170": ["HO/79", "06:43:18", "Trinh", "Maceap"], "0171": ["011", "Penale", "Conternational", "international", "Trimin", "na"], "0172": ["6/7079 40", "06:43:26", "Gian", "DD , Commin", "1010"], "0173": ["6/070", "06:43:30"], "0174": ["HU/VINH", "06:45:12"], "0175": ["HT/V79HD", "06:45:19"], "0176": [], "0177": ["HT/V9HD", "06:45:27", "7312 19:00 19:33:20"], "0178": ["H017900", "06:45:33", "C\u1ed1c", "\u0110I\u1ec0U"], "0179": ["6/717980", "06:45:36"], "0180": ["60", "CH\u01af\u01a0NG TR\u00ccNH 60 GI\u1ea6Y", "6/0079:0", "18:30 TR\u1ea6N CI77 H73", "0645:41", "T\u1ed4NG", "Th\u1ea7y T\u00e2y", "1.9", "191", "A", "1", "1", "1", "TO\u00c1N", "\u0110I.I", "10", "11", "V9", "4"], "0181": ["T\u1ed4NG TR\u00ccNH 60 GI\u1ea6Y", "HGLV", "TREN", "1"], "0182": ["HG/V9", "06/15:51", "T. M/pa", "0433ap"], "0183": ["HG/79", "0645:58", "(-c-)", "INTERNATIONAL"], "0184": ["HG/79", "06:46:05", "(G9)", "INTERNATIONAL"], "0185": ["H0/79", "06:46:09", "1", "900", "Penale", "Internation", "al", "International", "Criminal", "Court", "1", "4"], "0186": ["6/7/7979", "06:46:12", "107", "N7", "SIN", "8"], "0187": ["HT/079", "06:46:16", "E", "a", "VINIMINA", "VANIA"], "0188": ["67707900", "0646:17"], "0189": ["6/017920", "06/46:24"], "0190": ["67707900", "06:46:30"], "0191": ["Gi\u1eddi79:0", "06:46:36", "aaa", "a", "Gaaaaaaa", "7", "THANH 12 MIEN", "HE", "CDC EYE DROP WARNING"], "0192": ["CDC", "th\u1eddi gian", "Q", "1", "HEALTHADVISORY", "1", "06:46:39", "SOURCE: EZRICARE-INFO.COM"], "0193": ["CDC", "Ho\u00e0ng 1, Ho\u00e0ng Thu\u1ef7", "CDC", "HEALTHADVISORY", "06:46:46", "Co", "Artificia", "Tears", "SOURCE: EZRICARE-INFO.COM", "CDC EYE DROP WARNING"], "0194": ["CDC", "HT/V9HL", "EALTHADVISO", "ORY", "06:46:51", "HE", "artificia", "SOURCE: EZRICARE-INFO.COM", "CDC EYE DROP WARNING"], "0195": ["704", "HGL7", "06:46:54", "CDC EYE DROP WARNING"], "0196": ["HG/V79HA", "06:46:59"], "0197": ["H7/7/7940", "06:47:06"], "0198": ["HG7/79", "06:47:10"], "0199": ["Thu\u1ed9i coa", "GILL", "18/000", "Bacteria"], "0200": ["9/HD", "1", "4/770", "06:47:23"], "0201": ["HGL7"], "0202": ["2407/07/0"], "0203": ["HT/V"], "0204": ["17/07900", "06:47:"], "0205": ["H07/79", "06:47:4"], "0206": ["CH\u01af\u01a0NG TR\u00ccNH 60 GIA", "H\u1ed3/79", "06:479"], "0207": ["CH\u01af\u01a0NG TR\u00ccNH 60 GI\u1ea6Y", "H0/707900", "1830 TR\u00caN CIT7", "06:47:41"], "0208": ["CH\u01af\u01a0NG TR\u00ccNH 60 GI\u1ea6Y", "HT/V79HD", "18:30 TR\u00caN H/T/7", "757/079"], "0209": ["CH\u01af\u01a0NG TR\u00ccNH 60 GI\u1ea6Y", "67717940", "1830 TR\u00caN", "06/47:53", "QUAI", "HAM"], "0210": ["HTL7", "06:48:00"], "0211": ["23", "7", "203", "6/077900", "1", "1", "0648:04", "1", "+", "2", "23", "9", "Ca", "ar", "3", "1", "1", "8", "1", "S\u1ed1 12", "1", "1", "1", "13"], "0212": ["HT/V79hl", "06:48:06"], "0213": ["1867079", "06:48:16"], "0214": [], "0215": ["10/H", "HG/V"], "0216": ["9/HD", "47770", "06:48:17"], "0217": ["HG/V", "06.484"], "0218": ["C H\u00e0", "HT/V", "0648:300"], "0219": ["HG/V", "QNH THANH", "06:48:34", "100", "C\u1ea3i", "10", "\u0111\u01b0\u1eddng", "LONDON", "TR\u01afC S\u00c1NG", "M\u1eecNG TH\u00c1NG CHAY RAMADAN"], "0220": ["1", "1", "Th\u1ecb h\u00e0"], "0221": ["Vin"], "0222": [], "0223": ["HI\u1ec0U TO\u00c0N", "06:48:48"], "0224": ["HGD7", "06:48:58"], "0225": [], "0226": ["HGD7", "06:49:"], "0227": ["HG/V", "6280", "G"], "0228": ["06:49:07"], "0229": ["770", "H\u0110", "06:49:14"], "0230": ["19/H2", "HG/V7", "06:49:21"], "0231": ["9 HD", "HG/V", "06:49:24"], "0232": ["HG/V79", "06:49:30", "P 11", "1", "T\u1ed4 8 T\u1ed4", "Tin \u1ee9", "TUIL", "3.181", "Thu da", "T\u1ed5 000", "ANH"], "0233": ["HG/V", "06:49:34"], "0234": ["BDI"], "0235": ["CH\u01af\u01a0NG TR\u1ec8NH 60 GI\u1ea6Y", "18:30 TR\u1ea6N CI\u1edc7 C179", "HGL7", "Q.", "06:49:39"], "0236": [], "0237": ["HT/V79HA", "06/49:46", "Owen s Bridge"], "0238": ["HO\u00c0NG TO\u00c1N", "06:49:50"], "0239": ["H\u1ed3/79", "06:49:56", "FLUDE", "BILL", "H\u1ed2 H\u00ccNH"], "0240": [], "0241": ["HG7/V79", "06:50:02"], "0242": ["H7/079:00", "06:50:06"], "0243": ["3", "Tinheld", "HOOLGE", "1", "1", "06:50:12", "33", "2"], "0244": [], "0245": [], "0246": ["LHE/V", "06:50:20"], "0247": ["69007900", "06:50:22", "TH\u1eca H\u00c0NH", "137", "C4"], "0248": [], "0249": ["399", "Ga"], "0250": [], "0251": ["6/7079", "06:56:33", "OGIER", "KE RALLY", "SEBAS", "MEXIC", "TISTIEN"], "0252": ["1867/0794", "06:56:38"], "0253": ["H0779", "06:56:49", "Gia"], "0254": ["HI/V79H", "06:56:56"], "0255": ["HT/V79hl", "06:56:57"], "0256": ["HG/V79H", "06:57:00"], "0257": ["H07/79H1", "06:57:03"], "0258": [], "0259": ["23", "1", "6390", "066,06"], "0260": ["17,0", "9", "639", "06"], "0261": ["LHO/V", "06:57", "7", "1", "09.", "61.030"], "0262": ["GE", "0", "HE PMART", "FIAT", "BNP PARIBAS"], "0263": ["HG\u00c0Y", "06:57:", "65/040"], "0264": ["18/07/07", "06:57:35", "1", "9", "65040"], "0265": [], "0266": ["H\u1ed3 79", "06:57:4", "133", "1"], "0267": ["HT/V9HD", "06:57:51", "VRIBAS", "20", "Sai", "33"], "0268": ["CJ007900", "06:57:55", "Ban", "139", "1"], "0269": ["HG/V", "06:58:00", "19.0", "3", "6390"], "0270": ["HGD79", "06:58:06"], "0271": ["HG/79", "06:58:08"], "0272": [], "0273": ["HT/V79hd", "06:58:21"], "0274": ["HT/V9HD", "06:58:24"], "0275": [], "0276": ["14/7079", "06:58:35"], "0277": [], "0278": ["0", "672", "06:58:39"], "0279": ["HOV9", "06:58:4"], "0280": ["HT/V79H1", "06:58:40", "SUBSCRIBED"], "0281": ["H\u1ed3/79H", "06:58:49", "1"], "0282": [], "0283": ["H7/17940", "06:58:56"], "0284": ["HG/V", "06:58:59"], "0285": ["H7/179h0", "06:59:02", "ai", "gi\u1ea7y", "771"], "0286": ["H7/7940", "06:59:08", "GA", "1", "gi\u00e2y", "772"], "0287": ["HG\u00c0Y", "06:59:7", "1"], "0288": ["HG/794", "06:59:", "PHAI", "TINH D\u01af\u01a0NG:", "NGH", "KHO", "PH\u00da N\u1eee TRONG TI\u1ec0N", "TI\u1ec0M L\u00c0M \u0110ER", "401", "13/000"], "0289": ["6/07079 HD", "06/59:20", "0979.880.400", "\u0110- C\u01a0M CHI\u1ebeN G\u00c0 X\u00d4LI", "MO", "ReNare Cella"], "0290": ["HT/079", "ReNa", "Care Cella", "06:59:2", "13323"], "0291": ["HG/V79", "06:59:26"], "0292": ["HG7/794", "06:59:33", "HN"], "0293": ["HG/79", "06:59:39"], "0294": ["0979.080.400", "\u0110 COM CHI\u1ebeN G\u00c0 X", "H7/V7", "06:59:4"], "0295": [], "0296": [], "0297": ["HT/V9H0", "06:59:57", "ai", "92", "gi\u00e2y", "771"], "0298": ["HT/V79hd", "07:00:0", "6", "9", "1", "17/1", "60", "7/7:"], "0299": ["06:59:38"], "0300": ["H\u1ed3/791", "06:59:", "T\u1ed4NG GIANNI", "INFANTING", "CH FIFA"], "0301": ["HGL7", "06:59:"], "0302": ["2079", "06:59:4"], "0303": ["H\u01af\u01a0N", "H7/V", "SUBSCRIBED"], "0304": ["CH\u01af\u01a0NG TR\u00ccNH 60 GI\u00c1", "1830 TREN", "HG/V", "06:59:41", "SUBSCRIBED"], "0305": ["CH\u01af\u01a0NG TR\u00ccNH 60 GI\u1ea6Y", "HO\u00c0NG TH\u1eca H\u00c0", "18:30 TREN", "06:59:50", "FIFA", "das"], "0306": ["CH\u01af\u01a0NG TR\u00ccNH 60 GI\u1ea6Y", "6", "H\u1ed3 79", "18:30 TREN", "H5/077:", "06:59:58"], "0307": ["CH\u01af\u01a0NG TR\u00ccNH 60 GI\u1ea6Y", "6", "HT/079", "18:30 TREN", "06:59:54"], "0308": ["HT/V79hl", "06:59:56", "FIFA", "VER", "POW", "1", "Co.op comminh cong cong cong cong cong cong cong cong cong cung cung cu", "1", "co"], "0309": ["HT/079", "06:59:58", "FIFO", "AP", "3", "18", "18"], "0310": ["10/000 102", "HG\u00f2n", "P.C"], "0311": ["S\u1ed1 11:20", "HG/V", "200"], "0312": [], "0313": [], "0314": [], "0315": [], "0316": [], "0317": ["H\u1ed3 791", "07400:"], "0318": ["H07790", "07:00:"], "0319": ["HG/791", "07:00", "TRUNG T\u00c2M TIN T\u1ee8C", "\u0110\u00c0I TRUY\u1ec0N H\u00ccNH TH\u00c0NH PH\u1ed0 H\u1ed2 CH\u00cdMINH"], "0320": ["min"], "0321": ["H017900", "064648", "E", "T\u00e2y T\u00e2y T\u00e2y", "1722", "3004"], "0322": ["00624000420", "1024", "9.0"], "0323": ["HG/79", "06:46:5", "U.S.Department of", "Health and Human Services", "Administration", "Drug", "\u0110", "Foodand D", "A"], "0324": ["HT/V9HN", "06:46:58", "Zavzpret", "(zavegepant)", "nasal spray"], "0325": ["H007900", "06:47:08"], "0326": ["H007900", "0647:08"], "0327": ["H\u1ed3/79h\u00e0", "06:47:07", "SALIVIO PARA MIGRANA"], "0328": ["G/5/07", "ALIVIO", "TO PARA MIGRANAS", "SPRA", "EFECT", "PRUEBA", "DEL", "ASA"], "0329": ["H\u1ed3/V79H", "06:4781", "ALIVIO", "A MIGRANA", "PARA", "R\u00c1PIDO", "NASAL DE EFECTO B", "SPRA", "PRUEBA"], "0330": ["0641"], "0331": ["140794", "06-47:18"], "0332": ["HG/VG", "gi\u1edd", "06:47:23"], "0333": ["HG/79", "CH\u0110", "06:47:28"], "0334": ["H\u1ed3 V79", "06:47:"], "0335": ["H\u1ed3 79", "06:47:33", "\u0110CBSN", "EV"], "0336": ["H\u1ed3/79", "06:47:38", "TRI\u1ec6U CON CH\u00daC", "H\u00c0NG", "M\u1ef9: D", "NEW", "ORD", "C\u00d3 TH\u1ec0 M\u00c1C COVID-11"], "0337": ["H\u1ed3 791", "06:47:", "Stud", "Rat", "Exposed", "Coronavirus"], "0338": ["HT/V9HL", "06:47:48", "NYC P", "Rats", "Study", "Finds", "OCBSN", "Exposed", "Coronavirus"], "0339": ["HT/V9H", "06:47:53", "NYC P", "Study", "Finds N", "Rats", "Exposed", "Coronavirus"], "0340": ["HI7 079H", "06:47:58", "Study", "Rats", "Finds", "NYC L", "Exposed", "Coronavirus"], "0341": ["H\u1ed3/079", "06:47:58"], "0342": ["HT/V9HD", "06:48:06", "Fo", "1", "CORONAVIRUS PANDEMIC", "STUDY:", "NYC RATS P", "FOUND", "9", "cov", "UT", "ATI"], "0343": ["Gi\u1eddi79:0", "06:48:08"], "0344": ["Gi\u1edd 7 Qu\u1ea3 Th\u00e0nh Ph\u00fa Thu\u1ef7 Qu\u1ea3ng Ninh", "06:48:12", "1"], "0345": ["6/007900", "06:48:17"], "0346": ["HT/V9H", "06:48:22"], "0347": ["HG7/79", "06:48:2"], "0348": ["H079", "06:48:9"], "0349": ["H\u1ed3 79h", "06:48:32", "T\u1ed4 T\u1ec8NH TR\u1ea0NG KH\u00c1NG", "M\u1ef8 BAN B\u1ed0", "C\u1ea8P", "CALIFORNIA", "V\u00cc L\u00da L\u00daT DI\u1ec6N R\u1ed8NG"], "0350": ["4079", "06:48:3", "1"], "0351": ["32", "HG/V", "06:48:39"], "0352": ["32", "HO\u00c0NG", "06:48:42"], "0353": ["HG/79", "06:48:4"], "0354": ["10/000", "06:48:52"], "0355": ["HG/V9", "06:48:52"], "0356": ["HO\u00c0NG T\u1ea0I", "06:48:57"], "0357": ["18/5207", "06:4859"], "0358": ["HT.794", "06:49:02"], "0359": ["HO\u00c0NG", "06:49:08"], "0360": ["HG/V9", "06:49:49:49:49"], "0361": ["H7/079HD", "06:49:13"], "0362": ["HT/V79hl", "06:49:13", "MERAPI PHUN TR\u00c0O", "NUI", "NG\u00c0Y RA \u0110\u00c1M M\u00c1Y N\u00d3NG CAO T\u1edcI 7 KM"], "0363": ["HT/V79HD", "06:49:22"], "0364": ["HT/V79hl", "06:49:21"], "0365": ["1", "17", "HT/V79H1", "06:49:32"], "0366": ["6/0707980", "0649:37"], "0367": ["6/7/7940", "06:49:42"], "0368": ["6/7/7079:0", "06:49:47"], "0369": ["67017940", "0649:49"], "0370": ["H0707900", "06:49:52"], "0371": ["40/707900", "06:49:57"], "0372": ["6/7/079 40", "06:50:02"], "0373": ["HT/V9HD", "06:50:07"], "0374": ["61007900", "06:50:08"], "0375": ["6/007900", "06:50:12"], "0376": ["6/007900", "06:50:16", "1"], "0377": [], "0378": [], "0379": ["6/079", "06:50:26", "CREV"], "0380": ["H07790", "06:50:3"], "0381": ["HI/12QU", "06:50:36", "Vang", "1"], "0382": ["H7 7 Q", "06:50:", "21/59", "1", "1"], "0383": [], "0384": ["H70790", "9.1"], "0385": ["H7/7079", "06:50:56"], "0386": ["H01790", "06:51"], "0387": ["HO\u00c0NG 1791", "06:51:06"], "0388": ["6/717900", "06:51:06"], "0389": ["19H0", "HG/7", "06:51:11"], "0390": ["16/5707", "06:51810"], "0391": ["H7/V79h\u00e0", "06:51:21"], "0392": ["18/07/79", "06:51:26", "NG\u01af\u1edcI", "BI\u1ebeT \u0110\u1ebeN", "B\u1ea2O", "T\u00c0NG \u0110\u1ecaA", "GI\u1eeeA NEW YORK"], "0393": ["6/017900", "06:51:31", "SUBSCURED"], "0394": ["H7/V79HL", "06:51:36", "2", "1426 E5T", "Facton", "FIN:", "WAT CY"], "0395": ["HI7/079", "06:51:39", "EDGCOMB", "STEED"], "0396": ["H7/079", "06:51:40", "1"], "0397": ["HT/079", "06:51:"], "0398": ["6/7079H0", "06:51:46"], "0399": ["HG/V79HL", "06:51:50", "1", "GATIO", "CHORCH"], "0400": ["HO/VINH", "06:51:51", "ENGRE", "GATION", "CHURCH"], "0401": ["HG/79", "06:51:52", "GID"], "0402": ["H7/V79h", "06:51:56", "Commerce"], "0403": ["H7/V79", "06:51:56", "Commerce", "0"], "0404": ["HG/79", "06:51:", "Tay", "1"], "0405": ["HT/V79H", "06:52:06", "KRYSTA", "QUIGE", "HAMBURGERS", "3"], "0406": ["H\u1ed3/079", "06:52:06"], "0407": ["HT/V9HL", "06:52:00", "11", "9.1"], "0408": ["H07/79", "06:52:0e", "2"], "0409": ["HO7 V7 9hi", "06:52:1", "a"], "0410": ["C HD", "47670", "06:52:16"], "0411": ["HOL7", "06:52:20"], "0412": ["HO/V9HN", "06:52:23"], "0413": ["HT/V79hl", "06:52:30", "HOL"], "0414": ["HG/794", "06:52:33"], "0415": ["HG7/79", "06:52:39"], "0416": ["HT/V79hl", "06:52:39"], "0417": ["HT/079", "06:52:40", "CHEN", "C\u00c1CH"], "0418": ["HO\u00c0NG", "06:52:4"], "0419": ["H7/V79hd", "06:52:41"], "0420": ["H7/V79hd", "06:52:50"], "0421": [], "0422": ["6/7079", "06:52:53"], "0423": ["HT/V79HD", "06:52:53"], "0424": ["47/079", "06:52:57"], "0425": ["HT/V9H", "06:53:00"], "0426": ["HT/V79HL", "06:53:02"], "0427": ["H7/079", "78011940", "1", "a", "771"], "0428": ["H7/079:0", "07:0194", "QP", "1", "7772"], "0429": ["HTVQHD", "07:0194", "gi\u1ea7y", "VIA"], "0430": [], "0431": ["H\u1ed3/79", "076018"], "0432": ["HG/V791", "076013"], "0433": ["HG/791"], "0434": ["HG/791"], "0435": [], "0436": ["H17/7900", "07:00:10", "1"], "0437": ["H7/V9HD", "07:00:13", "JOE", "BIDI"], "0438": ["VINT OF THE", "0", "15:002"], "0439": ["6/717940", "07:00:28", "Ei", "31"], "0440": ["6/717940", "07:00:28", "Ei", "\u0110", "31"], "0441": ["P. P.T1 P.P.T", "Tang 1, Thanh 1, Thanh Trang Trinh Thanh Thu Tranh Thu Hu Nam Trinh Thung Trinh Thung Trung Trung Trung Trung Trung Trung Hung Tr", "13.13", "6/007900", "07:00:25"], "0442": ["10179", "07:00:28"], "0443": ["6/017900", "07:00:28"], "0444": [], "0445": [], "0446": ["Virst Repurt"], "0447": ["HG/79", "07:00:38", "VFirst Repup", "111"], "0448": ["H7/079:0", "07:00:49", "6", "1", "gi\u00e2y", "771"], "0449": ["HI/79HD", "07:00:48", "A", "0", "1", "771"], "0450": [], "0451": ["HG/794", "07:00:50"], "0452": ["HG/791", "07:00:58", "TRUNG T\u00c2M TIN T\u1ee8C", "\u0110\u00c0I TRUY\u1ec0N H\u00ccNH TH\u00c0NH PH\u1ed0 H\u1ed2", "CH"]}