{"001": [], "002": ["Coith", "tuo"], "003": ["tu\u1ed5itn"], "004": ["tu\u1ed5itry"], "005": ["U", "Hoitmerv", "90", "10", "LIGH", "1", "TO.DI", "1010", "18/000"], "006": ["971", "IN", "G\u00d3C NH\u00ccN TR\u01afA NAY", "\u0110\u00e0 N\u1eafng s\u1eafn s\u00e0ng cho L\u1ec5 h\u1ed9i ph\u00e1o hoa DIFF 2023"], "007": ["371", "IN", "G\u00d3C NH\u00ccN TR\u01afA NAY", "\u0110\u00e0 N\u1eafng s\u1eafn s\u00e0ng cho L\u1ec5 h\u1ed9i ph\u00e1o hoa DIFF 2023"], "008": ["01", "Vind 1", "11/11", "1010", "39", "L\u00ca H\u1ed8I PH\u00c1O HOA QU\u1ed0C T\u1ed4", "\u0110\u00c0N", "ANG", "NA", "2028", "10", "G\u1ed0C NH\u1ec8N TR\u01afA NAY", "\u0110\u00e0 N\u1eafng s\u1eafn s\u00e0ng cho L\u1ec5 h\u1ed9i ph\u00e1o hoa DIFF 2023"], "009": ["Toilling", "17", "Li\u00ean", "G\u00d3C NH\u1ec8N TR\u01afA NAY", "\u0110\u00e0 N\u1eafng s\u1eafn s\u00e0ng cho L\u1ec5 h\u1ed9i ph\u00e1o hoa DIFF 2023"], "010": ["1", "P.C"], "011": ["La 971", "0"], "012": ["9", "Thu\u1ef7", "1/1", "G\u1ed0C NH\u1ec8N TR\u01afA NAY", "Nhi\u1ec1u tr\u1ea3 m\u1eafc tay ch\u00e2n mi\u1ec7ng \u0111\u1ed9 n\u1eb7ng, \u0111\u00e3 c", "c\u00f3 1 b\u00e9 5 tu\u1ed5i t\u1eed vong"], "013": ["9", "10/370", "G\u00d3C NH\u1ec8N TR\u01afA NAY"], "014": ["11", "Ninca", "1"], "015": ["tu\u1ed5itn", "3", "4/0", "1", "19", "G\u00d3C NH\u1ec8N TR\u01afA NAY", "Ph\u00e1t hi\u1ec7n x\u01b0\u1eddng s\u1ea3n xu\u1ea5t th\u1ef1c ph\u1ea9m ch\u1ee9c n\u0103ng kh\u1ee7ng t\u1ea1i H\u00e0 N\u1ed9i"], "016": ["u\u1ed5i trerv", "UC", "1"], "017": ["11", "Saugy", "8", "G\u00d3C NH\u1ec8N TR\u01afA NAY", "T\u1ed5 nh\u00f3m \u0111\u00e1nh b\u1ea1c", "Tri\u1ec7t ph\u1ea3 \u1ed5", "c\u1ea9m \u0111\u1ea7u \u1edf t\u1ea7ng h\u00e0m kh\u00e1ch s\u1ea1n 5 sao", "do ng\u01b0\u1eddi n\u01b0\u1edbc ngo\u00e0i"], "018": ["13", "01", "1", "73", "58", "1", "G\u1ed0C NH\u00ccN TR\u01afA NAY", "\u0111\u00e1nh", "t\u1ea7ng h", "Sau"], "019": ["11", "Ch", "Tran"], "020": ["tu\u1ed5i tre", "G\u1ed0C NH\u00ccN TR\u01afA NAY", "C\u1ed1 g\u1eafng \u0111\u1ebfn c\u0169ng \u0111\u1ec1 gi\u00e0nh l\u1ea1i s\u1ef1 s\u1ed1ng cho con"], "021": ["NGI\u1edcI", "110", "Tren", "G\u00d3C NA"], "022": ["tu\u1ed5itr", "72", "1", "1", "G\u00d3C NH\u00ccN TR\u01afA NAY"], "023": [], "024": ["tu\u1ed5itn", "7", "1", "7", "G\u00d3C NH\u00ccN TR\u01afA NAY"], "025": ["tu\u1ed5itr", "D\u1ec5n ch\u01b0\u01a1ng tr\u00ecnh NH\u00c0 CH\u00c2N"], "026": ["tu\u1ed5itn"], "027": ["tu\u1ed5itru", "1", "G\u1ed0C NH\u00ccN TR\u01afA NAY"], "028": ["110", "101", "1", "7", "97", "G/0", "C3"], "029": ["tuoiun", "VIA", "1"], "030": [], "031": ["11", "61", "2000"], "032": ["932", "13/73"], "033": ["11133", "47", "1", "1177/77", "1010", "11", "471", "1111013", "11:000 18:00"], "034": ["ng\u00e0y", "5222", "T\u1ed4NG TI\u1ec0N TI\u1ec0N", "Vinh anh giang cong cong cong cong cong cu", "371", "1", "Tang 1 Thanh", "Commerce", "MINIT", "TITIONATE", "EP", "HELLNESS", "VII"], "035": ["6 2", "1", "WELLNESS", "CENT", "59", "3"], "036": ["Vingar", "2", "10"], "037": ["0", "10/070"], "038": ["11", "1", "\u0111\u1ed3ng", "1"], "039": ["11", "J7", "1", "Tang", "G\u00f2i", "ch\u0103m s\u00f3c", "00", "kho", "s\u1ee9c", "Ch", "00", "09", "00"], "040": ["tuoitrerv", "111", "1010", "11", "Tang", "chan", "Cio", "31"], "041": ["Ju\u1ed5i trerv"], "042": ["11", "971", "TIN"], "043": ["u", "H\u1ed3i", "atrerv", "1"], "044": ["tu\u1ed5i trerv", "CI", "m", "1", "COLLECTION", "BY BEST WESTERN", "CHARM RESORT H\u1ed2 TR\u00c0M", "T\u00c1C TR\u1eca LI\u1ec6U", "S\u1ee8C KH\u1eceE", "TU", "T\u00c1I T\u1ea0O N\u0102NG L\u01af\u1ee2NG \u0110\u0102NG C\u1ea8P T\u1ea0I H\u1ed2 TR\u00c0M"], "045": [], "046": ["tuoitn", "00"], "047": ["tuoitn", "1", "G\u00d3C NH\u00ccN TR\u01afA NAY"], "048": [], "049": ["01", "37", "1", "15", "2"], "050": ["3700", "Li", "NGOC NHIN TRUA NAY", "\u0110\u00e0 N\u00e0ng s\u1ea3n s", "Thoa DIFF 2023", "s\u00e0ng cho L", "h\u1ed9i ph\u00e1o hi", "Tang 2"], "051": ["tu\u1ed5i tren", "HO", "11", "N", "0", "A", "DL", "1", "1", "C", "Q", "1", "G\u1ed0C NH\u00ccN TR\u01afA NAY", "\u0110\u00e0 N\u1eafng s\u1eafn s\u00e0ng cho L\u1ec5 h\u1ed9i ph\u00e1o hoa DIFF 2023"], "052": ["tu\u1ed5itrerv", "C\u1ea9m", "1", "52,400", "13", "019", "10.00", "107"], "053": [], "054": [], "055": [], "056": ["tuoitr", "97"], "057": ["TRUY\u1ec0N", "1", "\u0110\u1ea0I T\u00c1 PHAN NG\u1eccC"], "058": ["tu\u1ed5i h\u1ecdry"], "059": ["tuc", "Turan"], "060": ["110", "t\u1ed5ng ti\u1ec1n"], "061": ["tu\u1ed5", "371", "UN"], "062": ["tuoitre", "1", "1"], "063": ["tu\u1ed5i tre"], "064": ["tu\u1ed5itre"], "065": [], "066": ["371", "UN", "1"], "067": ["371", "01", "FIN"], "068": ["371", "FIN", "1"], "069": ["A", "1", "19", "1"], "070": ["1", "668", "667 6", "094", "0", "1", "1", "0", "TL", "1"], "071": ["LIOI", "P.IN", "E", "1", "1", "1969", "7", "P/QNG", "855", "1", "1940", "1", "1", "6375008", "Filigian"], "072": [], "073": ["971", "TIN", "L\u00ca H\u1ed8I PH\u1ea2O HO\u00c1 QN", "DANA", "WG", "2029"], "074": ["971", "10", "L\u00ca H\u1ed8I PH\u1ea2O HO\u00c1 QU\u1ea2N", "DANA", "WG", "204", "23", "Trung u\u1ef9 L\u00ea v\u0169 Qu\u1ed1c \u0110\u1ea1t", "C\u00e1n b\u1ed9 C\u00f4ng an ph\u01b0\u1eddng N\u1ea1i Hi\u00ean \u0110\u00f4ng, qu\u1eadn S\u01a1n", "TP \u0110\u00e0 N\u1eafng", "L\u00ea v\u0169 qu\u1ed1:"], "075": ["971", "L\u00ca H\u1ed8I PH\u1ea2O HO\u00c1 QU\u1ea2N", "DANI", "NG", "204", "2", "T\u1ed5 1 V\u00f5 Qu\u1ed1c \u0110\u00e1"], "076": ["971", "L\u00ca H\u1ed8I PH\u1ea2O HO\u00c1 Q", "204", "2", "T\u1ed5ng 11 v\u00f5 qu\u1ed1c \u0111\u00e3"], "077": ["971", "QU\u00ca H\u1ed8I PH\u1ea2O HO\u00c1 CA", "23", "40"], "078": ["tu\u1ed5itre", "0", "1", "0", "0", "1", "LIGI", "0", "H", "TOIDE", "1010", "18/000"], "079": ["1", "3"], "080": ["1", "13"], "081": ["371", "UN"], "082": ["C1", "Vinery", "7917", "LIA", "L\u00ca H\u1ed8I PH\u1ea2O HO\u00c1 CA", "U\u1ed0C", "QUO", "DANA", "ANG", "2023", "10", "G\u1ed0C NH\u00ccN TR\u01afA NAY", "Cao Nguy\u00ean", "Th\u1ee5c hi\u1ec7n:", "Anh Thu"], "083": [], "084": [], "085": ["3 7", "G\u00d3C NH\u00ccN TR\u01afA N\u00c0", "NA"], "086": ["371", "IN", "P.CHO", "1", "323", "FIEE"], "087": ["371", "1 N", "Co", "1980", "13/7", "+", "H\u1ee2 \u0110I"], "088": ["tu\u1ed5itre", "1080", "10", "1", "Tiger"], "089": ["tu\u1ed5i", "79802", "1", "Tiger", "1", "\u0110\u1ea5u gi\u00e1 1 ki \u1ed1t ch\u1ee3 \u0110\u00e0 L\u1ea1t", "G\u1ed0C NH\u00ccN TR\u01afA NAY", "Kh\u1edfi \u0111i\u1ec1m 25 tri\u1ec7u, tr\u00fang \u0111\u1ea5u gi\u00e1 h\u01a1n 2 t\u1ec9 \u0111\u1ed3n", "18.000"], "090": ["971", "IN", "C", "Goa", "19614, \u0110\u1ecbnh", "T\u1ed4 \u0110\u00c0 L\u1ea0I"], "091": [], "092": ["11", "C", "3/", "1"], "093": ["371"], "094": ["tuc", "76", "4", "Lao", "10", "00", "1"], "095": ["tuc", "VN 971", "3", "P:", "6700"], "096": ["P.C2 P. P.C2 P. P. C\u1ea9m Q. TP. TP. Thu\u1ef7 QNH", "ASI"], "097": ["1", "Gia", "1", "1"], "098": ["TAS", "STO", "222222233 233"], "099": [], "100": ["T\u1ed5i trn", "TAST"], "101": ["10", "Cii", "TASTY"], "102": ["tu\u1ed5i tre"], "103": ["tu\u1ed5i tre"], "104": ["tu\u1ed5i tre"], "105": ["tu\u1ed5i trerv", "VietinBan:", "1"], "106": ["tu\u1ed5i tren", "Ng\u00e0n H", "Tong Cong huong", "VietinBank", "coa", "C\u1ea9m"], "107": ["tu\u1ed5i tren", "Ng\u00e0n H ng Cong huy", "Dong 1", "VietinBank", "108", "1"], "108": ["1", "2", "SAN"], "109": [], "110": ["tuc", "2"], "111": ["tuoitrerv"], "112": ["tuoitr", "1"], "113": [], "114": ["tuoitre", "G\u00d3C NH\u00ccN TR\u01afA NAM"], "115": ["tuoitn", "1"], "116": ["- 5 7", "G\u00d3C NH\u00ccN TR\u01afA NAY"], "117": ["1"], "118": [], "119": ["CII", "NAY"], "120": ["tuoitn"], "121": ["371"], "122": ["371"], "123": ["tuoi tre", "G\u00d3C NH\u1ec8N TR\u01afA NAY", "Nhi\u1ec1u tr\u1ea3 m\u1eafc tay ch\u00e2n mi\u1ec7ng \u0111\u1ed9 n\u1eb7ng, \u0111\u00e3 c", "c\u00f3 1 b\u00e9 5 tu\u1ed5i t\u1eed vong"], "124": ["971", "TIN", "10", "1"], "125": ["971", "TIN", "1", "TE", "9", "040"], "126": ["971", "TIN", "1", "\u0110E 1", "9"], "127": ["tu\u1ed5i", "37", "11"], "128": ["tu\u1ed5i tren"], "129": ["1", "TV", "- CAP"], "130": ["971", "TN", "00", "6", "P.Co", "01"], "131": ["371", "1", "0", "Tong", "1"], "132": [], "133": ["Vinert", "11"], "134": ["Tu\u1ed5i trerv", "11"], "135": ["Ci", "11", "370"], "136": ["371", "IN", "03"], "137": ["31", "IN", "1", "3, 13:", "1"], "138": [], "139": [], "140": ["3200", "010", "700", "KHU KH\u00c1M THEO Y\u1ec0U C\u1ea6U 2", "Sequest Clinic 2", "G\u1ed0C NH\u00ccN TR\u01afA NAY", "Th\u1ef1c hi\u1ec7n: M\u1ef9 Th\u01b0\u01a1ng", "Thu\u1ef5"], "141": ["Toin", "17", "11", "272", "KHU KH\u00c1M THEO Y\u1ec0U C\u1ea6U 2", "Squest Clinic 2", "PHANA", "G\u1ed0C NH\u00ccN TR\u01afA NAY", "Th\u1ef1c hi\u1ec7n: M\u1ef9 Th\u01b0\u01a1ng", "Th\u01b0 Tr\u1ea7n"], "142": ["tuoitrerv", "1020", "15:03:30", "83", "\u0110i", "00", ". Tp", "po", "0", "FL", "\u0110\u1ed3ng c\u1ea9m", "311", "7", "8", "9", "G\u00d3C NH\u1ec8N TR\u01afA NAY", "Th\u1ef1c hi\u1ec7n: M\u1ef9 Th\u01b0\u01a1ng", "Th\u01b0 Tr\u1ea7n"], "143": ["tuoitn"], "144": ["S\u1ed0C NH\u00ccN TR\u01afA NAY"], "145": ["tuoiti", "1"], "146": ["371", "IN", "A3", "Q.1", "90"], "147": ["970", "Tin"], "148": ["GOO", "C NH\u00ccN", "TRUA", "NAY", "A", "eno"], "149": [], "150": ["tu\u1ed5i", "Turg"], "151": ["tu\u1ed5it", "11 37"], "152": ["tu\u1ed5i tren"], "153": ["6110", "37"], "154": [], "155": ["tu\u1ed5i tre", "371", "Th\u00e0y Nguy\u1ec5n T\u1ea5n Ho\u00e0i B\u1ea3o", "Gi\u00e1o vi\u00ean T\u1ed5ng ph\u1ee5 tr\u00e1ch \u0110\u1ed9i, Tr\u01b0\u1eddng ti\u1ec1u h\u1ecdc Nguy\u1ec5n Th\u00e1i S\u01a1n (qu\u1eadn 3, TP.HCM)"], "156": ["tu\u1ed5i tren"], "157": [], "158": [], "159": ["tu\u1ed5i"], "160": ["60"], "161": [], "162": ["97", "IN", "LOCHA", "MAN H\u00ccNH"], "163": ["37", "In", "TH\u00c0NH LINH"], "164": [], "165": [], "166": ["tuoitre", "37"], "167": ["tu\u1ed5i", "37", "\u0110inh H\u1eefu Ho\u00e0ng Tu\u1ea5n", "hcm", "Nguye"], "168": ["tuoi", "111"], "169": ["Cuoit", "437"], "170": ["13/00", "171"], "171": ["9", "Thu\u1eadn"], "172": ["1", "+G"], "173": ["T\u1ed5i th", "tuo", "733", "3", "3", "2-33", "G\u00d3C NH\u00ccN TR\u01afA NAY", "Th\u1ef1c hi\u1ec7n: Ng\u1ecdc Ph\u01b0\u1ee3ng", "Thu Tr\u1ea7n"], "174": ["an", "Fiail"], "175": ["Di", "11"], "176": ["tu\u1ed5itn"], "177": ["tuoitn", "1", "1", "G\u00d3C NH\u00ccN TR\u01afA NAY"], "178": ["0"], "179": [], "180": ["G\u1ed0C NH\u00ccN TR\u01afA NAY"], "181": ["tu\u1ed5i trer", "1", "St-42"], "182": ["tu\u1ed5i tren", "G\u1ed0C NH\u00ccN TR\u01afA NAY", "Ph\u00e1t hi\u1ec7n x\u01b0\u1eddng s\u1ea3n xu\u1ea5t th\u1ef1c ph\u1ea9m ch\u1ee9c n\u0103ng kh\u1ee7ng t\u1ea1i H\u00e0 N\u1ed9i"], "183": ["tu\u1ed5itn", "13", "1", "106", "G\u1ed0C NH\u00ccN TR\u01afA NAY", "Ph\u00e1t hi\u1ec7n x\u01b0\u1eddng s\u1ea3n xu\u1ea5t th\u1ef1c ph\u1ea9m ch\u1ee9c n\u0103ng kh\u1ee7ng t\u1ea1i H\u00e0 N\u1ed9i"], "184": ["tu\u1ed5itr", "1", "1777"], "185": ["tu\u1ed5itre", "1", "9", "1"], "186": ["tu\u1ed5i trer", "0", "1", "1", "72", "V9 SO3n 73", "V9/0/503073", "Ng\u00e0y s\u1ed1 3.19", "INVINT", "2", "3", "1", "0", "0", "0", "1", "7", "Vso3n75", "4580222070", "Ninfood", "3NNAYSO3073", "7", "MINING SO3AT9", "836/772 Thanh Thanh", "3NN/VSO3019", "0", "S\u1ed1", "G", "1", "0", "1", "15/3/2020 000 18/000", "3NIWVSO3M79", "15157770000m4008", "SNIWNSOINTS", "3NNAVSO3M75", "FNIWVSOINT9", "151377 108/310405", "3NNVSO3NT9", "+ GLUCOSAMINE", "1", "SUPPLEMENT FACTS"], "187": ["1", "1", "tu\u1ed5i trerv", "1", "GANG COS PHANAN", "E", "GANG COS NHANG ANH", "5", "272", "GLUCOSAMINE", "8", "COMME", "SUPPLEMENT FACTS", "300000", "1072", "1", "18", "004502008", "Giang Same", "CT", "1", "GLUCOSAMAE", "C7", "1", "13", "COSANNAE", "Cap", "3/004/000", "1", "C", "1/0", "GLUCOSAMINE"], "188": ["11 20", "1", "tu\u1ed5i trerv", "60", "GANG COSMMART", "GANCOSMMART", "43", "1573", "13", "GLUCOSAMINE", "3", "MINE", "SUPPLEMENT FACTS", "30ANH C\u01a1 Tr\u1ea7n", "077", "1", "B", "10/00450200", "C7", "GIACAS DAMANAN", "72", "GI\u1ed0COSAMAE", "17", "1", "1963", "GOSANMAE", "1", "Co", "3/000 1960 19", "1", "Gri", "GI\u1ed0COSAMINE"], "189": ["tu\u1ed5i tre", "97", "1"], "190": ["tu\u1ed5i trerv"], "191": ["110", "Noitrerv"], "192": ["Vucitron", "5C:", "15", "QU\u00ca L\u1eecA FC"], "193": ["tuoit", "V 1"], "194": ["tu\u1ed5itre"], "195": ["tu\u1ed5i tren", "3.10", "a", "2", "\u0110", "1", "1", "5"], "196": ["Tan Anh Trinh Thu Bi Bi Thi Ha Kinh Ninh Ninh", "Tai an da da da dan dan toi toi toi tai thi Hai Hai Khu Ha Ki Ha Khu Ha Nam Noi Ha Nam Nam Nam Ay", "T\u1ed4NG C\u1ea8M TR\u1eca TR\u1eca TR\u1eca TR\u1eca TR\u1eca TR\u1eca TR\u1eca TR\u1eca H\u1ed2NG NH\u00c0NH NINH", "Cuoc cuc cuc cuc cu cu cu den tri tri the khu minh khu da Hien Hien Ninh Ninh Ninh Ninh Ninh", "Thanh chu trinh thanh thanh trinh thu Minh thanh da khu du khu thu trinh thu thu thu trinh thu thu tu tu tu tu tu tu tu tu tu tu ", "tuoi", "Thanh chu trinh thanh thanh thanh thanh da khu cu du a khu cu cu cu cu cu cu cu cu cu cu cu cu cu cu cu cu cu cu cu cu cu cu cu c", "Giang thanh thanh thanh thanh thanh trinh chu du du du du trinh thu du du tu du tu du du du anh thu thu tu du du du du du ang thu", "1", "Siniminimal and 18/10/10/10/000 - 14 - - 2020", "1", "Tanh 18/00/000 thanh 10/000 da 16 - 4, - 4, - 4, - - 12, KM", "1", "1", "Thanh chu anh trinh ninh cong cong a A KHA", "1", "1", "1", "Ng\u00e0y 10, 10 Khu 1, Khu Anh Ha Ha Khu A", "1", "Commerce", "Vinh du an da khu du du an du khu du tu du du an tu du du a du du a du a du a du a du a a du au du ang cu au du a du au au au au ", "C", "1", "1"], "197": ["tu\u1ed5i tic", "97", "10", "9"], "198": ["tuoitre", "97", "1"], "199": ["tu\u1ed5iti", "VIN"], "200": ["JF", "IN", "2 2"], "201": ["tu\u1ed5i tre", "1", "AN:", "E", "19", "7"], "202": ["tu\u1ed5ith", "J21", "1"], "203": ["TV"], "204": ["VM V"], "205": ["S\u1ed1 18/2020", "0"], "206": ["9/00", "E 1", "QU\u00ca L\u1eecA FC", "100", "G\u1ed0C NH\u00ccN TR\u01afA NAY", "Th\u1ef1c hi\u1ec7n: M\u1ef9 Th\u01b0\u01a1ng", "- Di\u1ec5m H\u01b0\u1eddng"], "207": ["tuoitier", "G\u1ed0C NH\u00ccN TR\u01afA NAY", "Th\u1ef1c hi\u1ec7n: M\u1ef9 Th\u01b0\u01a1ng", "- Di\u1ec5m H\u01b0\u1eddng", "2070"], "208": [], "209": ["tuoitr", "Tang", "1", "G\u00d3C NH\u00ccN TR\u01afA NAY"], "210": ["630"], "211": [], "212": ["Cuoit", "Tunern"], "213": ["tu\u1ed5i tren", "G\u00d3C NH\u00ccN TR\u01afA NAY", "B\u1eaft giam c\u00f2 \u0111\u1ea5t l\u1eeba \u0111\u1ea3o h\u01a1n 3 t\u1ef7 \u0111\u1ed3ng"], "214": ["N\u1ed5i", "11", "atrerv", "G\u1ed0C NH\u00ccN TR\u01afA NAY", "B\u1eaft giam c\u00f2 \u0111\u1ea5t l\u1eeba \u0111\u1ea3o h\u01a1n 3 t\u1ef7 \u0111\u1ed3ng"], "215": ["DI PA NAX"], "216": ["tu\u1ed5i trerv"], "217": ["tu\u1ed5i tre"], "218": ["tu\u1ed5i tre"], "219": [], "220": [], "221": [], "222": ["tu\u1ed5i tren", "G\u1ed0C NH\u00ccN TR\u01afA NAY", "Cao Nguy\u1ec5n", "- Mai Huy\u1ec1n", "Thuc hi\u1ec7n:"], "223": ["tu\u1ed5i trerv", "G\u1ed0C NH\u00ccN TR\u01afA NAY", "- Mai Huy\u1ec1n", "Cao Nguy\u00ean", "Th\u1ef1c hi\u1ec7n: C"], "224": ["G\u1ed0C NH\u00ccN TR\u01afA NAY"], "225": ["tuoitn", "1"], "226": ["G\u00d3C NH\u00ccN TR\u01afA"], "227": ["tu\u1ed5it", "11"], "228": ["G\u1ed0C NH\u1ec8N TR\u01afA NAY", "nh\u00f3m \u0111\u00e1nh b\u1ea1o", "Tri\u1ec7t ph\u00e1", "T\u1ed5 \u0111\u1ea7u \u1edf t\u1ea7ng h\u00e0nh", "do ng\u01b0\u1eddi n\u01b0\u1edbc ngo\u00e0i", "kh\u00e1ch", "san"], "229": [], "230": [], "231": [], "232": [], "233": [], "234": ["9158 4", "9:042", "04415"], "235": ["tu\u1ed5i tren"], "236": ["tuoitre"], "237": [], "238": ["1"], "239": ["110", "371"], "240": [], "241": ["almoigh", "1"], "242": [], "243": ["U A", "C:", "6"], "244": ["9", "G\u00f2", "71102"], "245": ["971", "TIN", "1", "Commit"], "246": ["1010", "A3", "Saining"], "247": ["1", "NG\u1ed0C NH\u00ccN TR\u01afA NAY", "Mai Huy\u1ec7n", "Nguy\u1ec5n"], "248": ["tuoitre", "971", "gi", "9", "G", "Thu\u1ef7", "Tia", "SHIT", "1", "10", "33", "SC\u0110", "G\u1ed0C NH\u00ccN TR\u01afA NAY", "- Mai Huy\u1ec1n", "Cao Nguy\u00ean", "Thuc hi\u1ec7n: ("], "249": ["tuo", "\u1ed5i tri", "911", "3", "1", "Suc", "1", "Gia", "SC\u0110", "G\u1ed0C NH\u1ec8N TR\u01afA NAY", "- Mai Huy\u1ec1n", "Cao Nguy\u00ean", "Thuc hi\u1ec7n:"], "250": [], "251": ["u\u1ed5i tren", "110"], "252": ["tu\u1ed5", "CI"], "253": ["IOI", "huy\u1ec7n", "h\u1ed3 ch\u00ed minh", "San Bau", "1", "Toan", "T\u00e2y", "09", "SAN BAY", "Saigon"], "254": ["1300", "1", "1", "1", "1", "Co", "47", "1", "1", "To\u00e1n", "\u0110\u1ebfn khi", "1", "1", "1", "nh\u1eadn nh\u00e0", "1930", "66633", "10/000", "0828 87 88 89", "1", "9", "\u0110 J charmlonghai.vn"], "255": [], "256": ["HO", "Gi"], "257": ["tu\u1ed5itr"], "258": ["tu\u1ed5itru", "C\u00daT \u0110\u1edcI TH\u01af\u1edcNG"], "259": ["tuoitn"], "260": ["3"], "261": [], "262": ["Toan", "1", "R\u01afA NAY"], "263": [], "264": ["C\u1ed0C NH\u00ccN TR\u01afA NAY"], "265": ["tu\u1ed5i tre"], "266": ["tu\u1ed5i tre", "G\u1ed0C NH\u00ccN TR\u01afA NAY", "C\u1ed1 g\u1eafng \u0111\u1ebfn c\u0169ng \u0111\u1ec1 gi\u00e0nh l\u1ea1i s\u1ef1 s\u1ed1ng cho con"], "267": ["tu\u1ed5i tren"], "268": ["tuoiti"], "269": ["tu\u1ed5itn"], "270": ["tu\u1ed5i tre"], "271": ["QUOITI"], "272": ["tuoiti"], "273": [], "274": [], "275": ["Soitre", "tu\u1ed5", "69 2"], "276": ["tuoith", "0-01", "169 5"], "277": ["tuoit"], "278": ["TRI\u1ec0U", "B\u00ean Th\u1ecb Bu\u1ef7 Th\u1ecb H\u1ed3 T\u00e2y", "30:00", "3", "Saugan", "1"], "279": ["11", "GAIGI", "TRI\u1ec0U", "1", "12", "1", "Th\u1ecb", "a"], "280": ["tu\u1ed5i tren"], "281": ["tu\u1ed5i tren"], "282": ["tu\u1ed5i tren", "Ch\u1ecb Ph\u00fang T", "Th\u1ecb Hu\u1ec7"], "283": ["tu\u1ed5i tren"], "284": ["tu\u1ed5i tren"], "285": ["tu\u1ed5i tren"], "286": ["Th\u1ecb gia", "10"], "287": ["tu\u1ed5i tre"], "288": ["tu\u1ed5i tren"], "289": ["tu\u1ed5i tren"], "290": [], "291": [], "292": ["tuoit", "15", "Neumart Cong commerce", "TRI\u1ec0U", "T\u1ea6N T\u1ec8", "4"], "293": ["010", "tuo", "P. P\u1ed9i Th\u1ecb", "VI\u00caN X CO S\u1ece", "T\u1ed4 T\u00c2N TR\u1ea2", "E", "320", "9.ARK", "5-0"], "294": ["tu\u1ed5i trerv", "L\u1ea7n", "3", "KHU V\u01afC", "H\u00c0NH CH\u1ec8NH", "QU\u1ea6Y S\u1ed0:", "QU\u1ea6Y S\u1ed0"], "295": ["tu\u1ed5i trerv", "E", "3", "KHU V\u1ef0C", "H\u00c0NH CH\u00cdNH", "TO\u00c1Y S\u1ed0 1", "QU\u1ea6Y S\u1ed0 3", "QU\u1ea6Y S"], "296": ["7"], "297": ["1", "11", "0707 52 55 75"], "298": ["tu\u1ed5i tr\u00ea"], "299": ["tu\u1ed5i tren"], "300": ["tu\u1ed5i treTV"], "301": ["tu\u1ed5i tren"], "302": ["tu\u1ed5i tren"], "303": ["tu\u1ed5i tren", "VJ.011"], "304": ["tu\u1ed5i tre"], "305": ["tu\u1ed5i tren"], "306": ["tu\u1ed5i tre", "Ch\u1ecb Ph\u00fang Th\u1ecb Hu\u1ec7", "M\u1eb9 c\u1ee7a Anh Th\u01b0, b\u1ec7nh nhi B\u1ec7nh vi\u1ec7n"], "307": ["tu\u1ed5i tren"], "308": ["tu\u1ed5i tren"], "309": [], "310": [], "311": [], "312": [], "313": ["tu\u1ed5i tren"], "314": ["tu\u1ed5i trerv"], "315": ["tu\u1ed5i tren"], "316": ["tuoitn"], "317": ["tuoiti"], "318": ["tu\u1ed5i tre"], "319": ["tuoitret"], "320": ["tuo", "Toith"], "321": ["110", "1070"], "322": ["tu\u1ed5i tren", "VALITTING"], "323": ["tu\u1ed5i tren", "VGHT (VD) TH\u1eca H\u1ed2NG TI\u1ec0N TI\u1ebeN TI\u1ebeN TI\u1ebeN TI\u1ebeN TI\u1ebeN TI\u1ebeN ANH) THU\u1ef7 THU\u1ef7 NINH) TH\u1eca THU\u1ef7 TI\u1ebeN TH\u1eca TI\u1ebeN HU\u1ef7 TI\u1ec6N TI\u1ebeN TI\u1ebeN TI\u1ebeN TI\u1ebeN TI"], "324": ["tu\u1ed5i tre", "3/"], "325": ["TT."], "326": ["971", "G\u1ed0C NH\u00ccN TR\u01afA NAY", "hien:", "T\u1ed5ng Li\u00ean"], "327": ["9", "Vingry"], "328": ["tu\u1ed5i tri", "2", "2", "G\u1ed0C NH\u00ccN TR\u01afA NAY"], "329": ["tu\u1ed5itn"], "330": ["tu\u1ed5i tr\u00ea", "1", "1", "G\u00d3C NH\u00ccN TRUA NAY"], "331": [], "332": ["31 -", "G\u00d3C NH\u00ccN TR\u01afA NAY"], "333": ["tu\u1ed5itr"], "334": ["tu\u1ed5iti"], "335": ["Ch\u1ecbu tr\u00e1ch nhi\u1ec7m ch\u01b0\u01a1ng tr\u00ecnh", "NH\u00c0 B\u00c1O XU\u00c2N TO\u00c0N", "Ch\u1ecbu tr\u00e1ch nhi\u1ec7m n\u1ed9i dung", "NH\u00c0 B\u00c1O V\u0169 B\u00ccNH", "G\u1ed0C NH\u00c0", "TRUA NAY"], "336": ["121", "phim", "H\u00c0I TRI\u1ec0U", "D\u1ef1ng phim", "ANH TH\u01af", "D\u1eabn ch\u01b0\u01a1ng tr\u00ecnh", "NH\u00c0 CH\u00c2N", "\u0110\u1ecdc l\u1eddi b\u00ecnh", "TRINH TR\u00c0"], "337": ["tu\u1ed5iti", "HU\u1ed8I", "11", "N", "G\u00d3C NH\u00ccN TR\u01afA NAY"]}