{"001": ["C1017900", "06:30:24"], "002": ["HGI79:0", "06:30:28"], "003": ["HO/V"], "004": ["HI/V9", "06:30:35", "1", "gia", "0", "712"], "005": ["HT/79", "06:30:4", "6", "60", "H\u1ed2NG LOAN", "PHAN NY", "VA", "77"], "006": ["H77/V", "088", "83", "03"], "007": ["HG/V9", "06:30:44"], "008": ["H5/V79", "06:3045"], "009": [], "010": ["10/0802"], "011": ["1", "A", "437", "13/000", "1", "1", "06:31:00", "1.20", "47"], "012": ["C2", "19", "1"], "013": ["H0770", "06:31:09", "A", "f"], "014": ["HT/79", "06:31:09", "VIA"], "015": ["H7/709", "06:31:16", "1", "1", "1"], "016": [], "017": ["Haivong", "06:31:"], "018": ["H5/079", "06:3127", "CON", "B\u1ed0 \u0110I\u1ec0M", "IN 80 \u0110A", "CHU"], "019": ["HG/79", "31:32"], "020": ["H0029", "06:31:34"], "021": ["19707900", "06:31:37"], "022": ["H0/79", "411", "1", "113"], "023": ["Cogi7 cao", "06:31:44"], "024": ["10179 cao", "06:31:45"], "025": ["HI/V9", "06:31:4", "1", "1", "1", "3", "19", "1", "1"], "026": ["HG/79", "06:31:52", "1", "1", "1", "3", "1"], "027": ["HT/79", "06:31:56", "G/", "1", "1", "1", "1", "3"], "028": ["HIVIT", "06:32:00"], "029": ["VITIVATEST", "06:32:05"], "030": ["NITVATEST", "06:32:08"], "031": ["COLLAYEST", "06:32:15", "Bang", "1363", "1", "NEWS"], "032": [], "033": ["H7/V79H1", "06:32:23"], "034": ["3/677/79", "06:32:26", "QN", "1", "13"], "035": ["116"], "036": ["660 + CH\u01af\u01a0NG TH\u00c0NH QU\u1ea6Y", "6/0020", "18:30 TR\u1ea6N CI\u1edc7 C179", "06:82-98", "1", "1", "GP:"], "037": ["CH\u01af\u01a0NG TR\u00ccNH 60 GI\u1ea6Y", "60", "6/7179", "18:070 TR\u1ea6N CIG 7 C179", "gi\u1edd", "06:32:37"], "038": ["Ng\u00e0y 179 20", "06:32:44"], "039": [], "040": ["H77/V70", "06.32:80", "11", "91", "1", "E", "nghi\u1ec7n", "Clici", "1"], "041": ["CH/57/V", "06:32:58"], "042": ["HT/V79", "06:32:51"], "043": ["6/0179", "06:33:02", "SUBSCRIBED"], "044": ["HT/V9", "06:33:06", "Nang Mii"], "045": ["Gi\u1eddi79 ap", "06:33:08"], "046": [], "047": ["HG77", "06:33:", "ANA", "1", "K", "0", "5", "1020", "1", "1", "1", "2"], "048": ["H/5/07", "06:33:1"], "049": ["1"], "050": ["HO\u00c0NG", "06:33:24"], "051": ["H5/79", "06:33:27", "1", "14", "1", "1", "1", "1", "3"], "052": ["19/000", "06:33:34", "1", "1", "1", "1", "1", "1", "1", "1"], "053": [], "054": ["1.000 1060", "06:33:39", "18", "33", "Sain", "4"], "055": ["40", "HG/79", "gi\u1edd", "06:33:45", "3"], "056": ["Cogi79 co", "06:38:48", "3:", "3", "C3", "1", "4", "2"], "057": ["G/7070", "06:33:5"], "058": ["7", "H\u1ed3 17/2000", "06:33:54", "1"], "059": [], "060": [], "061": ["HG/V", "06:34:02", "(0"], "062": ["HT/V9", "06:34:07", "9"], "063": ["1"], "064": ["HT/V9HD", "06:34:13", "1", "1", "1"], "065": ["6/7079 40", "06:34:21"], "066": ["0/0/00"], "067": ["Hol79", "06:3430"], "068": [], "069": ["HG/79", "06:34:39", "1", "15", "1", "3", "33"], "070": ["HG/79", "06:34:39"], "071": ["H7/V9H0", "06:34:42", "1", "1", "1"], "072": ["HG/79", "06:3449", "1", "1", "1", "1"], "073": ["H7/709H0", "06:3454", "1", "1"], "074": ["Tai", "600179 co", "Tr\u1ea7n", "06:34:58"], "075": ["15:", "20/000", "06:35:00", "42", "12", "1", "12/04", "Figa", "10", "2", "18/00", "3.2", "1", "1", "32", "SA", "790", "11", "6 C29"], "076": ["HG/V9", "06:35:02", "X\u1ebeP \u0110", "TR\u1ed2NG S\u1ea6U RI\u1ec0NG", "PH\u00ca DUY", "H\u00c0NG:", "CHO"], "077": ["T\u00e2y", "106", "1", "HT/V9", "1", "06935:06", "K. Q.000", "1", "X\u1ebeP", "TR\u1ed0NG S\u1ea6U RI\u1ec0NG", "V\u00d2NG T", "H\u00c0NG T", "PH\u00ca DU\u00dd", "CHOI", "Gia"], "078": ["1"], "079": ["517", "CH\u01af\u01a0NG TR\u00ccNH 60 GI\u1ea6Y", "HG/79", "06:35:1"], "080": ["18/00", "6000001000", "CH\u01af\u01a0NG TR\u00ccNH 60 GI\u1ea6Y", "HITVIND", "101774000", "06:35:1"], "081": ["HT/79", "06:35:15", "1", "236"], "082": ["Sind", "HT/V9", "06:35:1", "1", "VAN", "Th\u1ecb", "19"], "083": ["1", "HT/79", "06:35:18"], "084": ["HG/V79", "06:35:2"], "085": ["N7", "ng\u00e0y", "15", "15", "Coa", "06:05:21", "CA"], "086": ["HT/V70", "06:35:28", "Food", "/0", "21", "7", "A", "27", "7", "1", "ng\u00e0y"], "087": ["18/79", "06:35:26", "V7/000"], "088": ["6/5/70", "06:35:30"], "089": ["HO\u00c0NG", "HD", "06:35:34", "09:3A"], "090": ["3:32 - 2021", "44/023:22"], "091": ["G\u00f2m 10/00", "CH\u0110", "06:35:39"], "092": ["HIVO", "F06:35:"], "093": ["HT/V9", "06:35:4", "8", "17", "11", "1.3", "6"], "094": ["HG/79", "06:35:46"], "095": [], "096": [], "097": ["VITTO", "06:35"], "098": ["HTMIND", "06:35:57"], "099": ["HT/V9", "06:36:06"], "100": ["HTM9HD", "06:36:08", "THEO"], "101": ["HG/79", "06:36:1", "THEO", "L\u1ec6NH CHUY\u1ec0N TI\u1ec0N", "GI\u1ea2I"], "102": ["HI7/79", "06:38:24", "1", "1", "1", "1", "1", "4", "1", "1"], "103": ["/C/C", "06:38:31", "1", "2"], "104": ["HT/V9", "06:38:38"], "105": ["6", "CH\u01af\u01a0NG TR\u00ccNH 60 GI\u00c1", "C10179 00", "18:30 TR\u1ea6N", "06:38:49", "tphcm", "NG\u01af", "CHIEL", "HUT"], "106": ["HT/V9", "06:38:48"], "107": ["HT/V9HD", "06:38:55"], "108": ["HO17900", "06:39:00"], "109": ["H\u1ed3/79", "06:39:04"], "110": ["HTV9", "06:39:10"], "111": ["HT/V9", "06:39:1"], "112": ["HT/79", "06:40:35", "1", "2", "72", "1", "1", "1", "44"], "113": ["H7/709H", "06:40:4", "1", "23", "1", "6", "1"], "114": ["H079", "06:40:"], "115": ["H\u1ed3 79", "T\u00c0I T", "NHAU T", "XET", "TH\u00c0NH PH\u1ed0 H\u1ed2 CH\u1ec8 MINH", "TRUNG L\u01af\u01a0NG"], "116": ["H7/V9", "06:40:58", "C09105"], "117": ["Co079 ao", "06:41:08"], "118": ["Co179:0", "06:41:06"], "119": [], "120": ["H\u1ed3/79", "06:41:1"], "121": ["HT/V79"], "122": ["HG/79"], "123": [], "124": ["HT/V9"], "125": ["6/779", "CI\u0110", "0641:42"], "126": ["10179", "06:41:49"], "127": ["H7/079 HD", "06:4154", "200", "THONG CUO", "502", "614.116", "0935,195", "1", "11", "TRA"], "128": ["20K", "37/04", "Ci\u1eddi V\u00e0 Qu\u1ea3", "06:41:58", "1", "S\u1eecA", "C\u00daC B\u1eca GIA", "NHAN"], "129": ["6/70/79", "GIE", "06:42:08", "/"], "130": ["ng\u00e0y", "20K", "S ezviz", "HG/VA", "anh", "2029", "3", "E", "1", "1", "CT", "FO"], "131": ["NG\u00c0Y S\u1eecA", "20K", "3362VIZ", "an", "HGL7", "Sang", "1", "9", "1", "1", "Ti", "2", "46", "2", "1"], "132": ["1"], "133": ["S\u1eecA", "1", "20K", "Stezviz", "6.22", "HG7", "1", "32", "1", "E", "19", "2", "6", "1", "1"], "134": ["06:42:27", "1", "1", "42", "1", "1", "1"], "135": ["HG/V9", "06:42:34", "1", "1", "1", "3", "1", "3", "1"], "136": ["HTV9", "06:42:38"], "137": ["HIV9", "C\u1ea9m", "06:42:43", "1", "7/00", "\u0110\u1ed4I", "B\u00ccNH D\u01af\u01a0NG: \u0110I\u1ec0U", "N\u1eee G\u00c0Y", "H\u00c0N", "NG", "RAI", "TO", "VU TROM C\u1ea8P V\u1ea6T"], "138": ["2022-09", "6/009", "06:42:5", "1"], "139": ["2022-09", "HANG", "06:42:55", "1", "1", "Ving", "200"], "140": ["HT/V9", "06:42:58", "ng\u00e0y", "1"], "141": ["20934", "9"], "142": ["2096", "000", "06:43:11", "Giang", "7", "32"], "143": ["2022-09", "10.06", "Ligian", "06:43:15", "1", "19"], "144": ["Gi\u1eddi79:0", "06:43:19"], "145": ["677179", "gi\u1edd", "06:43:26", "1"], "146": ["10179 co", "0643:30"], "147": ["HT/V9", "06:43:33", "3"], "148": ["HG/79", "06:43:3", "ENI", "CHUN", "DAN", "\u0110\u1ec0 CHI\u1ebeM \u0110O\u1ea0T T\u00c0I S\u00c0N"], "149": ["1416/274", "GA", "6.000", "Qu\u1ea3 TCo2", "400", "Cop", "000", "19 70", "19 7 a", "Ao", "Tu\u1ed5i 8Q."], "150": ["9 9", "HG/79", "06:43:48", "SUBSCRIBED"], "151": [], "152": ["HT/79", "06:43:59"], "153": ["HG/V9", "06:44:08"], "154": ["HG/79", "06:44:06"], "155": ["HT/79", "06:44:11", "Kim7 Thanh Ng\u00e0y", "Nguy\u1ec5n", "S A", "1998"], "156": ["Litzo", "06/4"], "157": ["Co0179 co", "06:44:19", "Phang 6", "Tang 1, Tp. Thu\u1ef7 thu\u1ef7", "XIXIX", "VMX"], "158": ["HG/V", "06:44:2", "HEO", "N\u1eee HO\u00c0NG ELIZABETH \u0110\u1ec6NH"], "159": ["HTV9", "06:44:26"], "160": ["Duong Ca"], "161": ["677/79", "V GI\u0110", "06:46:41"], "162": ["Cigi79ao", "06:46:48"], "163": [], "164": [], "165": ["HG/79", "06:47"], "166": [], "167": [], "168": ["HO779", "06:47"], "169": ["HE/V", "06:47:"], "170": [], "171": ["HT/79", "06:47:29", "1", "20"], "172": [], "173": ["HG/79"], "174": ["HE70", "06:47:4", "VITX-1720", "43/032", "23302/24", "10/000", "3.3"], "175": ["10179:0", "06:47:50"], "176": ["NG\u00c0Y 200", "06:47:57"], "177": ["H\u1ed3 179"], "178": ["6/7070", "06:48:07"], "179": ["10179:0", "06:48:11", "BANH: DONG NG\u01af", "I\u1ebeNG", "HO\u00c0NG ELIZABETH", "\u0110\u1ec0", "gian", "TI\u1ebeP T\u00daC T\u0102NG"], "180": ["1000", "06/48:15"], "181": ["QNH", "Ti\u1ec1n", "3", "109", "06:48:19", "2", "11 - 1", "Ti\u00ean"], "182": ["1", "1", "Sain", "17", "4", "+3", "HT/70", "Gia", "7", "06:48:26", "3", "Co", "1010", "Tin"], "183": ["129", "4", "3427", "Trin", "HG/70", "06:48:30", "1", "3", "1:", "111", "20/", "Thu\u1ef7"], "184": ["HT/V", "06:48:3"], "185": ["HG/79", "06:48:48"], "186": ["HE/V79", "06:48:40"], "187": ["HT/79", "06:48:58"], "188": ["HG/79", "06:48:5"], "189": ["HT7/079", "06:49:06"], "190": ["1", "06:49:07"], "191": ["06:49:1", "2", "1", "1", "1"], "192": ["H7670", "06:49:20"], "193": ["HT/9H0", "06:49:26"], "194": ["HIV9", "06:49:30"], "195": ["10179 : 0", "06:49:37"], "196": [], "197": ["HI7/9", "06:49:"], "198": ["HI79", "06:49:52"], "199": ["G/7/799", "06:49:56"], "200": [], "201": ["HG/79", "06:50:03"], "202": ["HT/V9", "06:50:04", "SA3", "1"], "203": ["HGL7", "06:50:07", "\u0110\u1ea1i", "1363", "1"], "204": ["HOWING", "06:50:11", "\u0110ay", "1"], "205": ["HT/VQND", "06:50:13", "333", "1"], "206": ["HT/V9H", "06:50:19"], "207": ["Vino", "V37", "2", "H\u0110", "06:50:26"], "208": ["77/17", "06:50:33"], "209": ["HG/79", "06:50:39"], "210": ["HT/V9", "06:50:44", "CHIEN"], "211": ["HG/79", "06:50:48"], "212": ["HITVIND", "06:50:50"], "213": ["HO/79", "06:50:53"], "214": [], "215": ["6/7/79", "7. CIE", "06:51:02"], "216": ["6/7/79", "7/ CJA", "06:51:06", "SUBSCRIBED"], "217": [], "218": ["HT/79", "06:51:10"], "219": ["1", "952"], "220": [], "221": [], "222": ["HT/7"], "223": ["HI/V9", "06:51:22"], "224": ["1", "Vi"], "225": []}